Workbook
Name WBSLINK_GOVERNED_RECORDS: 'MASTER DATA'!$A$1:$W$1624

Sheet 01 PROJECT
A1: HarbourLink Urban Transit Expansion
A3: Version 1 · Maya Chen, Owner Project Controls
A5: current mapping records | E5: unresolved versions | I5: export / outcome rows
A6: 1622 | E6: 263 | I6: 1623
A8: 4 of 6 reported work areas have both schedule and cost connections.
A9: OWNER WBS · relate the views, then inspect the source
A10: Reported work area | G10: Schedule | I10: Cost | K10: Packages
A11: 1.1 Guideway and Civil | G11: 180 | I11: 80 | K11: 10
A12: 1.2 Stations | G12: 179 | I12: 80 | K12: 11
A13: 1.3 Systems | G13: 180 | I13: 79 | K13: 10
A14: 1.4 Vehicles and Depot | G14: 179 | I14: 80 | K14: 10
A15: 1.5 Testing and Commissioning | G15: 180 | I15: Not found | K15: 10
A16: 1.6 Program Management | G16: Not found | I16: 80 | K16: 10
A18: Branch counts are distinct mapped source versions within each work area; a split can appear in several areas. Do not sum branches as project totals. Coverage is not progress or financial health.
A21: 1.5 Testing and Commissioning
A22: Confirm whether the missing governed relationship is expected or requires project-controls attention.
A25: 1.6 Program Management
A26: Confirm whether the missing governed relationship is expected or requires project-controls attention.
A30: Explore the four charts → | E30: Findings and exact Actions → | I30: Follow the evidence →
A33: Browse work areas → | E33: Original source records → | I33: All 21 worksheets →
A36: Combined cost / forecast totals remain withheld. Whole-version approval is separate from individual professional decisions. Original assertions, split targets and reporting history remain in the supporting sheets.
A40: Recorded publication identity · original cover values
A42: A2 | C42: ZP SYNERGY GROUP INC.
A43: A4 | C43: WBS↔LINK™
A44: A5 | C44: Premium Integrated Project Controls Workbook
A45: A7 | C45: HarbourLink Urban Transit Expansion
A46: A10 | C46: Workbook state
A47: B10 | C47: Approved version 1 · stable mapping reference MV-1 · APPROVED
A48: A11 | C48: Reporting / data date
A49: B11 | C49: 2026-06-30 (Contractor Programme Rev 0); 2026-06-30 (Cost & Forecast Control Accounts Rev 0); 2026-06-30 (Commercial Package Register Rev 0)
A50: A12 | C50: Approved by
A51: B12 | C51: Maya Chen, Owner Project Controls
A52: A13 | C52: Approved (UTC)
A53: B13 | C53: 2026-10-16 14:11
... A59: A22 | C59: Begin with 02 START HERE →

Sheet 02 START HERE
A1: START WITH ONE FINDING
A2: Approved version 1 · stable mapping reference MV-1 · APPROVED
A3: Owner Work Breakdown Structure (WBS): the approved project-work hierarchy. Source assertions, professional decisions and whole-version approval remain separate.
A5: Destination | B5: Use and counting population
A6: 03 EXECUTIVE VIEW | B6: Approved management position and four native charts.
A7: 04 ISSUES FOR REVIEW | B7: Exact governed matters and professional Actions; no materiality ranking.
A8: 09 WBS EXPLORER | B8: Primary scope navigation: distinct relationship coverage/status.
A9: 08 CROSSWALK | B9: Approved source-to-WBS targets; split targets are separate rows.
A10: 10 EVIDENCE & DECISIONS | B10: Source assertion, interpretation, contrary evidence and human decision.
A11: 07 CHANGES & REVALIDATION | B11: Relationship change classification and separate revalidation.
A12: 01 PROJECT | B12: Publication identity, approved version and source-set orientation; then open the index.
A13: 05 INTEGRATION HEALTH | B13: Cross-view relationship availability and gated analytical populations.
A14: 06 INTEGRATED PROJECT | B14: Supporting cross-view projections by WBS; use 09 for first scope navigation.
A15: 11 SOURCES & PROVENANCE | B15: Approval-time source revisions and representation integrity.
A16: 12 ASSURANCE | B16: Withholding, metric ledger, evidence boundary and reconciliation.
... A25: 15 ANALYSIS | B25: Advanced filter/formula analysis; not the executive first-use summary.
A28: Why relationship and row counts differ
A29: Distinct current relationships: 1,622. Current target rows: 1,623. Historical-inclusive relationship versions: 1,622. All target rows: 1,623. 09 WBS EXPLORER counts distinct relationships; 14 WBS HIERARCHY counts relationship ROWS, including split targets and retired rows unless filtered.
A32: NEW PRACTITIONER | B32: Read the single executive position, then follow your actual WBS scope to its evidence and any explicit withholding. Use the destinations above; no example-specific outcome is prescribed.
B35: Population definitions are in A29. Distinct relationships and relationship ROWS are different populations.

Sheet 03 EXECUTIVE VIEW
A1: EXECUTIVE VIEW
A2: Project: HarbourLink Urban Transit Expansion · Owner Work Breakdown Structure (WBS): the approved hierarchy of project work.
A3: Executive | C3: Issues | E3: Integration | G3: Project
A4: Changes | C4: Crosswalk | E4: Evidence | G4: Sources
A5: APPROVED PROJECT POSITION
A6: Approved version 1 · stable mapping reference MV-1 · APPROVED · Maya Chen, Owner Project Controls
A7: 4 of 6 Owner-WBS work areas have both schedule and cost relationships.
A8: Coverage describes relationships, not project progress, health or zero cost.
A9: Testing and Commissioning: schedule present · cost relationships ABSENT
A10: Program Management: cost present · schedule relationships ABSENT
A11: 1,622 current relationships · 0 retired versions · 1,622 historical-inclusive relationship versions.
A12: 1,623 current target rows · 1,623 all target rows. A split relationship has one row per target.
A13: Unresolved: 263 · Outside current WBS: 1 · No applicable WBS: 1.
A14: Exact recorded Action: Confirm whether the missing governed relationship is expected or requires project-controls attention.
A15: Exact recorded Action: Review the governed NEW_SCOPE outcomes in the project-controls context.
A16: Exact recorded Action: Use only conclusions that do not depend on these unresolved relationships.
... A19: 4 figures below support this position; detailed source tables follow the figures.
A21: 1 · Schedule and cost relationships by WBS branch | E21: 2 · Relationship outcomes by source
A23: 4 of 6 WBS branches carry both schedule and cost relationships; 2 branches are covered by only one of them. | E23: 1,357 of 1,622 current relationships relate a source record to a WBS element, across 3 source documents. 265 are recorded outside the WBS or left unresolved.
A26: Out of 6 reported WBS branches. Coverage is observed through the WBS; it is not a direct schedule-to-cost link. Detail: 05 INTEGRATION HEALTH. | E26: Out of 1,622 current relationships (retired relationships excluded); one relationship counted once even when split across several WBS elements. Detail: 08 CROSSWALK.
A51: 3 · No previous approved version to compare | E51: 4 · Outcomes left unresolved or outside the WBS
A53: No previous approved version is recorded, so all 1,622 relationships are new in this reporting baseline. The next cycle will show what carried forward and what changed. | E53: 265 of 1,622 current relationships are left unresolved or recorded outside the approved WBS. Rely only on conclusions that do not depend on them; sheet 04 groups them into the issues for review.
A56: Out of 1,622 relationships in this baseline, by change label. Detail: 07 CHANGES & REVALIDATION. | E56: Out of 1,622 current relationships (retired excluded). These are recorded, governed outcomes, not errors. Detail: sheet 04 (issues for review) and 08 CROSSWALK.
A83: CHART SOURCE TABLES AND POPULATION DEFINITIONS
A84: Each chart draws on the approved relationship records. It states what it counts, the population covered and the source table beneath it.
A86: 1 · Schedule and cost relationships by WBS branch
A87: 4 of 6 WBS branches carry both schedule and cost relationships; 2 branches are covered by only one of them.
A88: Out of 6 reported WBS branches. Coverage is observed through the WBS; it is not a direct schedule-to-cost link. Detail: 05 INTEGRATION HEALTH.
A104: WBS branches | C104: Count
A105: Schedule and cost | C105: 4
A106: Schedule only | C106: 1
A107: Cost only | C107: 1
A108: Neither schedule nor cost | C108: 0
A109: Total WBS branches | C109: 6
A111: 2 · Relationship outcomes by source
A112: 1,357 of 1,622 current relationships relate a source record to a WBS element, across 3 source documents. 265 are recorded outside the WBS or left unresolved.
A113: Out of 1,622 current relationships (retired relationships excluded); one relationship counted once even when split across several WBS elements. Detail: 08 CROSSWALK.
A129: Source document | C129: Related to a WBS element | E129: Recorded outside the WBS | G129: Left unresolved | I129: Total
A130: Commercial Package Register | C130: 60 | E130: 0 | G130: 0 | I130: 60
A131: Contractor Programme | C131: 898 | E131: 2 | G131: 182 | I131: 1082
A132: Cost & Forecast Control Accounts | C132: 399 | E132: 0 | G132: 81 | I132: 480
A133: All sources | C133: 1357 | E133: 2 | G133: 263 | I133: 1622
A135: 3 · No previous approved version to compare
A136: No previous approved version is recorded, so all 1,622 relationships are new in this reporting baseline. The next cycle will show what carried forward and what changed.
A137: Out of 1,622 relationships in this baseline, by change label. Detail: 07 CHANGES & REVALIDATION.
A153: Change label | C153: Count
A154: Carried forward | C154: 0
A155: Re-keyed, revalidated | C155: 0
A156: Changed, re-decided | C156: 0
A157: New | C157: 1622
A158: Retired | C158: 0
A159: Total relationships | C159: 1622
A161: 4 · Outcomes left unresolved or outside the WBS
A162: 265 of 1,622 current relationships are left unresolved or recorded outside the approved WBS. Rely only on conclusions that do not depend on them; sheet 04 groups them into the issues for review.
A163: Out of 1,622 current relationships (retired excluded). These are recorded, governed outcomes, not errors. Detail: sheet 04 (issues for review) and 08 CROSSWALK.
A179: Outcome | C179: Count
A180: Unresolved (UNSURE) | C180: 263
A181: Scope not in the approved WBS (NEW_SCOPE) | C181: 1
A182: No WBS element applies (NO_WBS) | C182: 1
A183: Unresolved or outside the WBS | C183: 265
A187: E01 · Owner-WBS branch | B187: Schedule relationships | C187: Cost relationships | D187: Coverage state
A188: 1.1 Guideway and Civil | B188: 180 | C188: 80 | D188: Both views present
A189: 1.2 Stations | B189: 179 | C189: 80 | D189: Both views present
A190: 1.3 Systems | B190: 180 | C190: 79 | D190: Both views present
A191: 1.4 Vehicles and Depot | B191: 179 | C191: 80 | D191: Both views present
A192: 1.5 Testing and Commissioning | B192: 180 | C192: 0 | D192: Cost coverage gap
A193: 1.6 Program Management | B193: 0 | C193: 80 | D193: Schedule coverage gap
A195: Coverage through the Owner WBS; not project health or direct schedule-to-cost equivalence. 2 have only one of these views.

Sheet 04 ISSUES FOR REVIEW
A1: ISSUES FOR REVIEW
A2: The issues the governed evidence supports raising with the project team now. Grouped by type and WBS code; not ranked by importance.
A3: Executive | B3: Issues | C3: Integration | D3: Project | E3: Changes | F3: Crosswalk | G3: Evidence | H3: Sources
A5: Matter | B5: Why it matters | C5: Affected WBS scope | D5: Affected source view(s) | E5: State | F5: Recommended professional action | G5: Evidence path | H5: Authority
A6: Schedule scope has no governed cost relationships | B6: This work area has relationships to one supplied control view but none to the other. Confirm whether that gap is expected. | C6: 1.5 Testing and Commissioning | D6: Schedule + Cost | E6: Derived observation from governed relationships | F6: Confirm whether the missing governed relationship is expected or requires project-controls attention. | G6: 05 INTEGRATION HEALTH / 08 CROSSWALK: WBS 1.5 | H6: Derived observation; no direct schedule-to-cost relationship asserted
A7: Cost scope has no governed schedule relationships | B7: This work area has relationships to one supplied control view but none to the other. Confirm whether that gap is expected. | C7: 1.6 Program Management | D7: Schedule + Cost | E7: Derived observation from governed relationships | F7: Confirm whether the missing governed relationship is expected or requires project-controls attention. | G7: 05 INTEGRATION HEALTH / 08 CROSSWALK: WBS 1.6 | H7: Derived observation; no direct schedule-to-cost relationship asserted
A8: 1 governed relationship outcome records NEW_SCOPE | B8: The approved relationship state records scope not represented by the current approved WBS. | C8: Outside current approved WBS | D8: See Crosswalk | E8: Professional/governed outcome | F8: Review the governed NEW_SCOPE outcomes in the project-controls context. | G8: 08 CROSSWALK: filter Relationship Type = NEW_SCOPE | H8: Governed relationship outcome
A9: 263 relationship outcomes remain unresolved | B9: The approved state preserves uncertainty rather than forcing a WBS relationship. | C9: See Crosswalk | D9: See Crosswalk | E9: Professionally/governed unresolved outcome | F9: Use only conclusions that do not depend on these unresolved relationships. | G9: 08 CROSSWALK / 10 EVIDENCE & DECISIONS | H9: Governed uncertainty
A11: Ordering note: matters are grouped by recorded issue type and WBS code. No claim of objective project materiality or #1 priority is made.

Sheet 05 INTEGRATION HEALTH
A1: INTEGRATION HEALTH
A2: Top-level work-area availability and attention counts by control view.
A3: Executive | B3: Issues | C3: Integration | D3: Project | E3: Changes | F3: Crosswalk | G3: Evidence | H3: Sources | K3: Where is professional attention concentrated?
K4: Where are governed reopened, unresolved or contradictory relationship populations concentrated?
A5: WBS | B5: Scope | C5: Schedule | D5: Cost / forecast | E5: Package / contract | F5: Integration condition | G5: Attention / unresolved | H5: Changed | I5: Evidence path | J5: Responsibility | K5: WBS | L5: Reopened | M5: Unresolved | N5: Contradictory | O5: Attention records
A6: 1.1 | B6: Guideway and Civil | C6: 180 governed relationships | D6: 80 governed relationships | E6: 10 governed relationships | F6: Aligned: Schedule and cost both relate through this WBS branch. 10 package/contract relationships also project through this branch. | G6: 0 | H6: 270 | I6: 06 INTEGRATED PROJECT / 08 CROSSWALK: WBS 1.1 | J6: Not supplied | K6: 1.1 | L6: 0 | M6: 0 | N6: 1 | O6: 1
A7: 1.2 | B7: Stations | C7: 179 governed relationships | D7: 80 governed relationships | E7: 11 governed relationships | F7: Aligned: Schedule and cost both relate through this WBS branch. 11 package/contract relationships also project through this branch. | G7: 0 | H7: 270 | I7: 06 INTEGRATED PROJECT / 08 CROSSWALK: WBS 1.2 | J7: Not supplied | K7: 1.2 | L7: 0 | M7: 0 | N7: 1 | O7: 1
A8: 1.3 | B8: Systems | C8: 180 governed relationships | D8: 79 governed relationships | E8: 10 governed relationships | F8: Aligned: Schedule and cost both relate through this WBS branch. 10 package/contract relationships also project through this branch. | G8: 0 | H8: 269 | I8: 06 INTEGRATED PROJECT / 08 CROSSWALK: WBS 1.3 | J8: Not supplied | K8: 1.3 | L8: 0 | M8: 0 | N8: 0 | O8: 0
A9: 1.4 | B9: Vehicles and Depot | C9: 179 governed relationships | D9: 80 governed relationships | E9: 10 governed relationships | F9: Aligned: Schedule and cost both relate through this WBS branch. 10 package/contract relationships also project through this branch. | G9: 0 | H9: 269 | I9: 06 INTEGRATED PROJECT / 08 CROSSWALK: WBS 1.4 | J9: Not supplied | K9: 1.4 | L9: 0 | M9: 0 | N9: 0 | O9: 0
A10: 1.5 | B10: Testing and Commissioning | C10: 180 governed relationships | D10: 0 governed relationships | E10: 10 governed relationships | F10: Attention: Schedule scope has no governed cost relationships in this WBS branch. 10 package/contract relationships also project through this branch. | G10: 0 | H10: 190 | I10: 06 INTEGRATED PROJECT / 08 CROSSWALK: WBS 1.5 | J10: Not supplied | K10: 1.5 | L10: 0 | M10: 0 | N10: 0 | O10: 0
A11: 1.6 | B11: Program Management | C11: 0 governed relationships | D11: 80 governed relationships | E11: 10 governed relationships | F11: Attention: Cost scope has no governed schedule relationships in this WBS branch. 10 package/contract relationships also project through this branch. | G11: 0 | H11: 90 | I11: 06 INTEGRATED PROJECT / 08 CROSSWALK: WBS 1.6 | J11: Not supplied | K11: 1.6 | L11: 0 | M11: 0 | N11: 0 | O11: 0
K12: Counts locate governed professional-attention populations only; they are not financial or schedule materiality rankings.
A14: One table above shows control-view coverage. Responsibility is retained in column J; professional-attention evidence is in columns K–O.
A25: V4 · COST / FORECAST VISUAL WITHHELD
A26: Withheld: current generic field-name recognition is not a governed quantitative contract. Measure meaning, currency/unit, period, grain, WBS basis, allocation and unresolved treatment must all be established.

Sheet 06 INTEGRATED PROJECT
A1: INTEGRATED PROJECT
A2: Detailed approved scope levels and their source relationship counts; use 09 WBS EXPLORER for primary navigation.
A3: Executive | B3: Issues | C3: Integration | D3: Project | E3: Changes | F3: Crosswalk | G3: Evidence | H3: Sources
A5: WBS | B5: Scope | C5: Schedule relationships | D5: Cost relationships | E5: Package / contract relationships | F5: Other relationships | G5: Open / unresolved | H5: Changed | I5: Current integration observation | J5: Drill to proof
B6: HarbourLink Urban Transit Expansion | C6: 898 governed relationships | D6: 399 governed relationships | E6: 60 governed relationships | F6: 0 governed relationships | G6: 0 | H6: 1357 | I6: Schedule and cost both relate through this WBS branch. 60 package/contract relationships also project through this branch. | J6: 08 CROSSWALK: WBS
A7: 1 | B7: HarbourLink Urban Transit Expansion | C7: 898 governed relationships | D7: 399 governed relationships | E7: 60 governed relationships | F7: 0 governed relationships | G7: 0 | H7: 1357 | I7: Schedule and cost both relate through this WBS branch. 60 package/contract relationships also project through this branch. | J7: 08 CROSSWALK: WBS 1
A8: 1.1 | B8: Guideway and Civil | C8: 180 governed relationships | D8: 80 governed relationships | E8: 10 governed relationships | F8: 0 governed relationships | G8: 0 | H8: 270 | I8: Schedule and cost both relate through this WBS branch. 10 package/contract relationships also project through this branch. | J8: 08 CROSSWALK: WBS 1.1
A9: 1.1.1 | B9: Guideway and Civil - Guideway Structures | C9: 120 governed relationships | D9: 40 governed relationships | E9: 0 governed relationships | F9: 0 governed relationships | G9: 0 | H9: 160 | I9: Schedule and cost both relate through this WBS branch. | J9: 08 CROSSWALK: WBS 1.1.1
A10: 1.1.1.1 | B10: Guideway Structures - East Segment | C10: 0 governed relationships | D10: 0 governed relationships | E10: 0 governed relationships | F10: 0 governed relationships | G10: 0 | H10: 0 | I10: No governed schedule or cost relationships in this WBS branch. | J10: 08 CROSSWALK: WBS 1.1.1.1
A11: 1.1.1.2 | B11: Guideway Structures - West Segment | C11: 0 governed relationships | D11: 0 governed relationships | E11: 0 governed relationships | F11: 0 governed relationships | G11: 0 | H11: 0 | I11: No governed schedule or cost relationships in this WBS branch. | J11: 08 CROSSWALK: WBS 1.1.1.2
A12: 1.1.2 | B12: Guideway and Civil - Utility & Roadworks | C12: 60 governed relationships | D12: 40 governed relationships | E12: 0 governed relationships | F12: 0 governed relationships | G12: 0 | H12: 100 | I12: Schedule and cost both relate through this WBS branch. | J12: 08 CROSSWALK: WBS 1.1.2
A13: 1.1.2.1 | B13: Utility & Roadworks - East Segment | C13: 0 governed relationships | D13: 0 governed relationships | E13: 0 governed relationships | F13: 0 governed relationships | G13: 0 | H13: 0 | I13: No governed schedule or cost relationships in this WBS branch. | J13: 08 CROSSWALK: WBS 1.1.2.1
A14: 1.1.2.2 | B14: Utility & Roadworks - West Segment | C14: 0 governed relationships | D14: 0 governed relationships | E14: 0 governed relationships | F14: 0 governed relationships | G14: 0 | H14: 0 | I14: No governed schedule or cost relationships in this WBS branch. | J14: 08 CROSSWALK: WBS 1.1.2.2
A15: 1.1.3 | B15: Guideway and Civil - Track Support Works | C15: 0 governed relationships | D15: 0 governed relationships | E15: 0 governed relationships | F15: 0 governed relationships | G15: 0 | H15: 0 | I15: No governed schedule or cost relationships in this WBS branch. | J15: 08 CROSSWALK: WBS 1.1.3
A16: 1.1.3.1 | B16: Track Support Works - East Segment | C16: 0 governed relationships | D16: 0 governed relationships | E16: 0 governed relationships | F16: 0 governed relationships | G16: 0 | H16: 0 | I16: No governed schedule or cost relationships in this WBS branch. | J16: 08 CROSSWALK: WBS 1.1.3.1
A17: 1.1.3.2 | B17: Track Support Works - West Segment | C17: 0 governed relationships | D17: 0 governed relationships | E17: 0 governed relationships | F17: 0 governed relationships | G17: 0 | H17: 0 | I17: No governed schedule or cost relationships in this WBS branch. | J17: 08 CROSSWALK: WBS 1.1.3.2
A18: 1.1.4 | B18: Guideway and Civil - Civil Interfaces | C18: 0 governed relationships | D18: 0 governed relationships | E18: 0 governed relationships | F18: 0 governed relationships | G18: 0 | H18: 0 | I18: No governed schedule or cost relationships in this WBS branch. | J18: 08 CROSSWALK: WBS 1.1.4
... A85: 1.6.4.2 | B85: Delivery Integration - Delivery Partners | C85: 0 governed relationships | D85: 0 governed relationships | E85: 0 governed relationships | F85: 0 governed relationships | G85: 0 | H85: 0 | I85: No governed schedule or cost relationships in this WBS branch. | J85: 08 CROSSWALK: WBS 1.6.4.2

Sheet 07 CHANGES & REVALIDATION
A1: CHANGES & REVALIDATION
A2: Recorded changes and the review they required. Carried-forward evidence is not individual confirmation of every source assertion.
A3: Executive | B3: Issues | C3: Integration | D3: Project | E3: Changes | F3: Crosswalk | G3: Evidence | H3: Sources
A5: Initial approved relationship state · current reporting baseline | D5: V3 · CYCLE CONTINUITY
A6: Carried forward | B6: 0 | D6: This is the initial approved relationship baseline; the counts at left describe the current governed state.
A7: Re-keyed, revalidated | B7: 0
A8: Changed, re-decided | B8: 0
A9: New | B9: 1622 | D9: All relationships shown as New were established in this initial baseline; they are not changes from a prior approved cycle.
A10: Retired | B10: 0
A12: Relationship | B12: Source | C12: Record | D12: WBS | E12: Change state | F12: Reopen / revalidation reason | G12: Decision provenance | H12: Evidence path
A13: R1563-v2 | B13: Commercial Package Register | C13: PKG-001 | D13: 1.1 Guideway and Civil | E13: New | G13: Maya Chen, Owner Project Controls | H13: 10 EVIDENCE & DECISIONS
A14: R1564-v1 | B14: Commercial Package Register | C14: PKG-002 | D14: 1.1 Guideway and Civil | E14: New | G14: Source assignment -- not individually reviewed | H14: 10 EVIDENCE & DECISIONS
A15: R1565-v1 | B15: Commercial Package Register | C15: PKG-003 | D15: 1.1 Guideway and Civil | E15: New | G15: Source assignment -- not individually reviewed | H15: 10 EVIDENCE & DECISIONS
A16: R1566-v1 | B16: Commercial Package Register | C16: PKG-004 | D16: 1.1 Guideway and Civil | E16: New | G16: Source assignment -- not individually reviewed | H16: 10 EVIDENCE & DECISIONS
A17: R1567-v1 | B17: Commercial Package Register | C17: PKG-005 | D17: 1.1 Guideway and Civil | E17: New | G17: Source assignment -- not individually reviewed | H17: 10 EVIDENCE & DECISIONS
A18: R1568-v1 | B18: Commercial Package Register | C18: PKG-006 | D18: 1.1 Guideway and Civil | E18: New | G18: Source assignment -- not individually reviewed | H18: 10 EVIDENCE & DECISIONS
A19: R1569-v1 | B19: Commercial Package Register | C19: PKG-007 | D19: 1.1 Guideway and Civil | E19: New | G19: Source assignment -- not individually reviewed | H19: 10 EVIDENCE & DECISIONS
A20: R1570-v1 | B20: Commercial Package Register | C20: PKG-008 | D20: 1.1 Guideway and Civil | E20: New | G20: Source assignment -- not individually reviewed | H20: 10 EVIDENCE & DECISIONS
A21: R1571-v1 | B21: Commercial Package Register | C21: PKG-009 | D21: 1.1 Guideway and Civil | E21: New | G21: Source assignment -- not individually reviewed | H21: 10 EVIDENCE & DECISIONS
A22: R1572-v1 | B22: Commercial Package Register | C22: PKG-010 | D22: 1.1 Guideway and Civil | E22: New | G22: Source assignment -- not individually reviewed | H22: 10 EVIDENCE & DECISIONS
A23: R1-v1 | B23: Contractor Programme | C23: SCH-01-001 | D23: 1.1.1 Guideway and Civil - Guideway Structures | E23: New | G23: Source assignment -- not individually reviewed | H23: 10 EVIDENCE & DECISIONS
A24: R10-v1 | B24: Contractor Programme | C24: SCH-01-010 | D24: 1.1.1 Guideway and Civil - Guideway Structures | E24: New | G24: Source assignment -- not individually reviewed | H24: 10 EVIDENCE & DECISIONS
... A1634: R999-v2 | B1634: Contractor Programme | C1634: SCH-06-099 | D1634: UNSURE | E1634: New | G1634: Maya Chen, Owner Project Controls | H1634: 10 EVIDENCE & DECISIONS

Sheet 08 CROSSWALK
A1: CROSSWALK
A2: Inspectable relationship truth: source record → governed relationship → WBS target. | O2: Literal source values only. Whole source account, not a target allocation. Repeated target rows must not be summed. Aggregate cost / forecast remains withheld.
A3: Executive | B3: Issues | C3: Integration | D3: Project | E3: Changes | F3: Crosswalk | G3: Evidence | H3: Sources
A5: Source | B5: Record | C5: Description | D5: Source assertion | E5: Relationship | F5: Target WBS | G5: Relationship type | H5: Lifecycle state | I5: Change | J5: Basis / origin | K5: Decided by | L5: Target status | M5: Contrary evidence | N5: Evidence & decisions | O5: Whole-source budget | P5: Whole-source forecast | Q5: Source currency | R5: Dedicated source basis | S5: Source as of | T5: Original source revision | U5: Exact source location | V5: Whole-source allocation boundary
A6: Commercial Package Register | B6: PKG-001 | C6: Guideway Civil Works | D6: Package Code = PK-101; WBS Code = 1.1;1.2 | E6: R1563-v2 | F6: 1.1 Guideway and Civil | G6: ONE_TO_MANY | H6: APPROVED | I6: New | J6: Professional decision | K6: Maya Chen, Owner Project Controls | M6: Source states 'WBS Code' = '1.1;1.2' -- names no element of this WBS -- professional reason (Maya Chen, Owner Project Controls): Source package register explicitly states both Owner-WBS branches. | N6: 10 EVIDENCE & DECISIONS
A7: Commercial Package Register | B7: PKG-002 | C7: Utility Relocations | D7: Package Code = PK-102; WBS Code = 1.1 | E7: R1564-v1 | F7: 1.1 Guideway and Civil | G7: ONE_TO_ONE | H7: APPROVED | I7: New | J7: Source assignment -- not individually reviewed | N7: 10 EVIDENCE & DECISIONS
A8: Commercial Package Register | B8: PKG-003 | C8: Road & Drainage | D8: Package Code = PK-103; WBS Code = 1.1 | E8: R1565-v1 | F8: 1.1 Guideway and Civil | G8: ONE_TO_ONE | H8: APPROVED | I8: New | J8: Source assignment -- not individually reviewed | N8: 10 EVIDENCE & DECISIONS
A9: Commercial Package Register | B9: PKG-004 | C9: Track Support Works | D9: Package Code = PK-104; WBS Code = 1.1 | E9: R1566-v1 | F9: 1.1 Guideway and Civil | G9: ONE_TO_ONE | H9: APPROVED | I9: New | J9: Source assignment -- not individually reviewed | N9: 10 EVIDENCE & DECISIONS
A10: Commercial Package Register | B10: PKG-005 | C10: Guideway Civil Works - Lot 2 | D10: Package Code = PK-105; WBS Code = 1.1 | E10: R1567-v1 | F10: 1.1 Guideway and Civil | G10: ONE_TO_ONE | H10: APPROVED | I10: New | J10: Source assignment -- not individually reviewed | N10: 10 EVIDENCE & DECISIONS
A11: Commercial Package Register | B11: PKG-006 | C11: Utility Relocations - Lot 2 | D11: Package Code = PK-106; WBS Code = 1.1 | E11: R1568-v1 | F11: 1.1 Guideway and Civil | G11: ONE_TO_ONE | H11: APPROVED | I11: New | J11: Source assignment -- not individually reviewed | N11: 10 EVIDENCE & DECISIONS
A12: Commercial Package Register | B12: PKG-007 | C12: Road & Drainage - Lot 2 | D12: Package Code = PK-107; WBS Code = 1.1 | E12: R1569-v1 | F12: 1.1 Guideway and Civil | G12: ONE_TO_ONE | H12: APPROVED | I12: New | J12: Source assignment -- not individually reviewed | N12: 10 EVIDENCE & DECISIONS
A13: Commercial Package Register | B13: PKG-008 | C13: Track Support Works - Lot 2 | D13: Package Code = PK-108; WBS Code = 1.1 | E13: R1570-v1 | F13: 1.1 Guideway and Civil | G13: ONE_TO_ONE | H13: APPROVED | I13: New | J13: Source assignment -- not individually reviewed | N13: 10 EVIDENCE & DECISIONS
A14: Commercial Package Register | B14: PKG-009 | C14: Guideway Civil Works - Lot 3 | D14: Package Code = PK-109; WBS Code = 1.1 | E14: R1571-v1 | F14: 1.1 Guideway and Civil | G14: ONE_TO_ONE | H14: APPROVED | I14: New | J14: Source assignment -- not individually reviewed | N14: 10 EVIDENCE & DECISIONS
A15: Commercial Package Register | B15: PKG-010 | C15: Utility Relocations - Lot 3 | D15: Package Code = PK-110; WBS Code = 1.1 | E15: R1572-v1 | F15: 1.1 Guideway and Civil | G15: ONE_TO_ONE | H15: APPROVED | I15: New | J15: Source assignment -- not individually reviewed | N15: 10 EVIDENCE & DECISIONS
A16: Contractor Programme | B16: SCH-01-001 | C16: West approach: track-slab survey - installation | D16: WBS Code = 1.1.1 | E16: R1-v1 | F16: 1.1.1 Guideway and Civil - Guideway Structures | G16: ONE_TO_ONE | H16: APPROVED | I16: New | J16: Source assignment -- not individually reviewed | N16: 10 EVIDENCE & DECISIONS
A17: Contractor Programme | B17: SCH-01-002 | C17: Depot lead: temporary traffic staging - inspection | D17: WBS Code = 1.1.1 | E17: R2-v1 | F17: 1.1.1 Guideway and Civil - Guideway Structures | G17: ONE_TO_ONE | H17: APPROVED | I17: New | J17: Source assignment -- not individually reviewed | N17: 10 EVIDENCE & DECISIONS
A18: Contractor Programme | B18: SCH-01-004 | C18: River crossing: road restoration - release | D18: WBS Code = 1.1.1 | E18: R4-v1 | F18: 1.1.1 Guideway and Civil - Guideway Structures | G18: ONE_TO_ONE | H18: APPROVED | I18: New | J18: Source assignment -- not individually reviewed | N18: 10 EVIDENCE & DECISIONS
... A135: Contractor Programme | B135: SCH-01-179 | C135: River crossing: guideway pier reinforcement - release | D135: WBS Code = 1.1.1 | E135: R179-v1 | F135: 1.1.1 Guideway and Civil - Guideway Structures | G135: ONE_TO_ONE | H135: APPROVED | I135: New | J135: Source assignment -- not individually reviewed | N135: 10 EVIDENCE & DECISIONS
A136: Cost & Forecast Control Accounts | B136: CST-01-001 | C136: Guideway and Civil - roadworks - professional services | D136: Cost Account = CA-1001; WBS Code = 1.1.1 | E136: R1083-v1 | F136: 1.1.1 Guideway and Civil - Guideway Structures | G136: ONE_TO_ONE | H136: APPROVED | I136: New | J136: Source assignment -- not individually reviewed | N136: 10 EVIDENCE & DECISIONS | O136: 347500 | P136: 347500 | Q136: CAD | S136: 2027-06-30 | T136: C1-R0 | U136: Supplied practice file monthly_cost_forecast.xlsx, row 2 | V136: Whole source account, not a target allocation. Repeated target rows must not be summed. Aggregate cost / forecast remains withheld.
A137: Cost & Forecast Control Accounts | B137: CST-01-003 | C137: Guideway and Civil - concrete structures - closeout | D137: Cost Account = CA-1003; WBS Code = 1.1.1 | E137: R1085-v1 | F137: 1.1.1 Guideway and Civil - Guideway Structures | G137: ONE_TO_ONE | H137: APPROVED | I137: New | J137: Source assignment -- not individually reviewed | N137: 10 EVIDENCE & DECISIONS | O137: 382500 | P137: 407500 | Q137: CAD | S137: 2027-06-30 | T137: C1-R0 | U137: Supplied practice file monthly_cost_forecast.xlsx, row 4 | V137: Whole source account, not a target allocation. Repeated target rows must not be summed. Aggregate cost / forecast remains withheld.
A138: Cost & Forecast Control Accounts | B138: CST-01-005 | C138: Guideway and Civil - temporary works - supply and install | D138: Cost Account = CA-1005; WBS Code = 1.1.1 | E138: R1087-v1 | F138: 1.1.1 Guideway and Civil - Guideway Structures | G138: ONE_TO_ONE | H138: APPROVED | I138: New | J138: Source assignment -- not individually reviewed | N138: 10 EVIDENCE & DECISIONS | O138: 417500 | P138: 417500 | Q138: CAD | S138: 2027-06-30 | T138: C1-R0 | U138: Supplied practice file monthly_cost_forecast.xlsx, row 6 | V138: Whole source account, not a target allocation. Repeated target rows must not be summed. Aggregate cost / forecast remains withheld.
A139: Cost & Forecast Control Accounts | B139: CST-01-007 | C139: Guideway and Civil - roadworks - allowance | D139: Cost Account = CA-1007; WBS Code = 1.1.1 | E139: R1089-v1 | F139: 1.1.1 Guideway and Civil - Guideway Structures | G139: ONE_TO_ONE | H139: APPROVED | I139: New | J139: Source assignment -- not individually reviewed | N139: 10 EVIDENCE & DECISIONS | O139: 452500 | P139: 477500 | Q139: CAD | S139: 2027-06-30 | T139: C1-R0 | U139: Supplied practice file monthly_cost_forecast.xlsx, row 8 | V139: Whole source account, not a target allocation. Repeated target rows must not be summed. Aggregate cost / forecast remains withheld.
A140: Cost & Forecast Control Accounts | B140: CST-01-009 | C140: Guideway and Civil - concrete structures - field package | D140: Cost Account = CA-1009; WBS Code = 1.1.1 | E140: R1091-v1 | F140: 1.1.1 Guideway and Civil - Guideway Structures | G140: ONE_TO_ONE | H140: APPROVED | I140: New | J140: Source assignment -- not individually reviewed | N140: 10 EVIDENCE & DECISIONS | O140: 487500 | P140: 487500 | Q140: CAD | S140: 2027-06-30 | T140: C1-R0 | U140: Supplied practice file monthly_cost_forecast.xlsx, row 10 | V140: Whole source account, not a target allocation. Repeated target rows must not be summed. Aggregate cost / forecast remains withheld.
A141: Cost & Forecast Control Accounts | B141: CST-01-011 | C141: Guideway and Civil - temporary works - professional services | D141: Cost Account = CA-1011; WBS Code = 1.1.1 | E141: R1093-v1 | F141: 1.1.1 Guideway and Civil - Guideway Structures | G141: ONE_TO_ONE | H141: APPROVED | I141: New | J141: Source assignment -- not individually reviewed | N141: 10 EVIDENCE & DECISIONS | O141: 522500 | P141: 547500 | Q141: CAD | S141: 2027-06-30 | T141: C1-R0 | U141: Supplied practice file monthly_cost_forecast.xlsx, row 12 | V141: Whole source account, not a target allocation. Repeated target rows must not be summed. Aggregate cost / forecast remains withheld.
A142: Cost & Forecast Control Accounts | B142: CST-01-013 | C142: Guideway and Civil - roadworks - closeout | D142: Cost Account = CA-1013; WBS Code = 1.1.1 | E142: R1095-v1 | F142: 1.1.1 Guideway and Civil - Guideway Structures | G142: ONE_TO_ONE | H142: APPROVED | I142: New | J142: Source assignment -- not individually reviewed | N142: 10 EVIDENCE & DECISIONS | O142: 557500 | P142: 557500 | Q142: CAD | S142: 2027-06-30 | T142: C1-R0 | U142: Supplied practice file monthly_cost_forecast.xlsx, row 14 | V142: Whole source account, not a target allocation. Repeated target rows must not be summed. Aggregate cost / forecast remains withheld.
A143: Cost & Forecast Control Accounts | B143: CST-01-015 | C143: Guideway and Civil - concrete structures - supply and install | D143: Cost Account = CA-1015; WBS Code = 1.1.1 | E143: R1097-v1 | F143: 1.1.1 Guideway and Civil - Guideway Structures | G143: ONE_TO_ONE | H143: APPROVED | I143: New | J143: Source assignment -- not individually reviewed | N143: 10 EVIDENCE & DECISIONS | O143: 592500 | P143: 617500 | Q143: CAD | S143: 2027-06-30 | T143: C1-R0 | U143: Supplied practice file monthly_cost_forecast.xlsx, row 16 | V143: Whole source account, not a target allocation. Repeated target rows must not be summed. Aggregate cost / forecast remains withheld.
A144: Cost & Forecast Control Accounts | B144: CST-01-017 | C144: Guideway and Civil - temporary works - allowance | D144: Cost Account = CA-1017; WBS Code = 1.1.1 | E144: R1099-v1 | F144: 1.1.1 Guideway and Civil - Guideway Structures | G144: ONE_TO_ONE | H144: APPROVED | I144: New | J144: Source assignment -- not individually reviewed | N144: 10 EVIDENCE & DECISIONS | O144: 627500 | P144: 627500 | Q144: CAD | S144: 2027-06-30 | T144: C1-R0 | U144: Supplied practice file monthly_cost_forecast.xlsx, row 18 | V144: Whole source account, not a target allocation. Repeated target rows must not be summed. Aggregate cost / forecast remains withheld.
A145: Cost & Forecast Control Accounts | B145: CST-01-019 | C145: Guideway and Civil - roadworks - field package | D145: Cost Account = CA-1019; WBS Code = 1.1.1 | E145: R1101-v1 | F145: 1.1.1 Guideway and Civil - Guideway Structures | G145: ONE_TO_ONE | H145: APPROVED | I145: New | J145: Source assignment -- not individually reviewed | N145: 10 EVIDENCE & DECISIONS | O145: 662500 | P145: 687500 | Q145: CAD | S145: 2027-06-30 | T145: C1-R0 | U145: Supplied practice file monthly_cost_forecast.xlsx, row 20 | V145: Whole source account, not a target allocation. Repeated target rows must not be summed. Aggregate cost / forecast remains withheld.
A146: Cost & Forecast Control Accounts | B146: CST-01-021 | C146: Guideway and Civil - concrete structures - professional services | D146: Cost Account = CA-1021; WBS Code = 1.1.1 | E146: R1103-v1 | F146: 1.1.1 Guideway and Civil - Guideway Structures | G146: ONE_TO_ONE | H146: APPROVED | I146: New | J146: Source assignment -- not individually reviewed | N146: 10 EVIDENCE & DECISIONS | O146: 697500 | P146: 697500 | Q146: CAD | S146: 2027-06-30 | T146: C1-R0 | U146: Supplied practice file monthly_cost_forecast.xlsx, row 22 | V146: Whole source account, not a target allocation. Repeated target rows must not be summed. Aggregate cost / forecast remains withheld.
A147: Cost & Forecast Control Accounts | B147: CST-01-023 | C147: Guideway and Civil - temporary works - closeout | D147: Cost Account = CA-1023; WBS Code = 1.1.1 | E147: R1105-v1 | F147: 1.1.1 Guideway and Civil - Guideway Structures | G147: ONE_TO_ONE | H147: APPROVED | I147: New | J147: Source assignment -- not individually reviewed | N147: 10 EVIDENCE & DECISIONS | O147: 732500 | P147: 757500 | Q147: CAD | S147: 2027-06-30 | T147: C1-R0 | U147: Supplied practice file monthly_cost_forecast.xlsx, row 24 | V147: Whole source account, not a target allocation. Repeated target rows must not be summed. Aggregate cost / forecast remains withheld.
... A175: Cost & Forecast Control Accounts | B175: CST-01-079 | C175: Guideway and Civil - roadworks - field package | D175: Cost Account = CA-1079; WBS Code = 1.1.1 | E175: R1161-v1 | F175: 1.1.1 Guideway and Civil - Guideway Structures | G175: ONE_TO_ONE | H175: APPROVED | I175: New | J175: Source assignment -- not individually reviewed | N175: 10 EVIDENCE & DECISIONS | O175: 1712500 | P175: 1737500 | Q175: CAD | S175: 2027-06-30 | T175: C1-R0 | U175: Supplied practice file monthly_cost_forecast.xlsx, row 80 | V175: Whole source account, not a target allocation. Repeated target rows must not be summed. Aggregate cost / forecast remains withheld.
A176: Contractor Programme | B176: SCH-01-003 | C176: Interface works near guideway and civil boundary | D176: WBS Code = 1.1.2 | E176: R3-v1 | F176: 1.1.2 Guideway and Civil - Utility & Roadworks | G176: ONE_TO_ONE | H176: APPROVED | I176: New | J176: Source assignment -- not individually reviewed | N176: 10 EVIDENCE & DECISIONS
A177: Contractor Programme | B177: SCH-01-006 | C177: West approach: retaining-wall excavation - installation | D177: WBS Code = 1.1.2 | E177: R6-v1 | F177: 1.1.2 Guideway and Civil - Utility & Roadworks | G177: ONE_TO_ONE | H177: APPROVED | I177: New | J177: Source assignment -- not individually reviewed | N177: 10 EVIDENCE & DECISIONS
A178: Contractor Programme | B178: SCH-01-009 | C178: River crossing: track-slab survey - release | D178: WBS Code = 1.1.2 | E178: R9-v1 | F178: 1.1.2 Guideway and Civil - Utility & Roadworks | G178: ONE_TO_ONE | H178: APPROVED | I178: New | J178: Source assignment -- not individually reviewed | N178: 10 EVIDENCE & DECISIONS
A179: Contractor Programme | B179: SCH-01-012 | C179: Depot lead: road restoration - inspection | D179: WBS Code = 1.1.2 | E179: R12-v1 | F179: 1.1.2 Guideway and Civil - Utility & Roadworks | G179: ONE_TO_ONE | H179: APPROVED | I179: New | J179: Source assignment -- not individually reviewed | N179: 10 EVIDENCE & DECISIONS
A180: Contractor Programme | B180: SCH-01-015 | C180: Central guideway: drainage tie-in - field start | D180: WBS Code = 1.1.2 | E180: R15-v1 | F180: 1.1.2 Guideway and Civil - Utility & Roadworks | G180: ONE_TO_ONE | H180: APPROVED | I180: New | J180: Source assignment -- not individually reviewed | N180: 10 EVIDENCE & DECISIONS
A181: Contractor Programme | B181: SCH-01-018 | C181: East portal: temporary traffic staging - turnover | D181: WBS Code = 1.1.2 | E181: R18-v1 | F181: 1.1.2 Guideway and Civil - Utility & Roadworks | G181: ONE_TO_ONE | H181: APPROVED | I181: New | J181: Source assignment -- not individually reviewed | N181: 10 EVIDENCE & DECISIONS
A182: Contractor Programme | B182: SCH-01-021 | C182: West approach: drilled-shaft installation - installation | D182: WBS Code = 1.1.2 | E182: R21-v1 | F182: 1.1.2 Guideway and Civil - Utility & Roadworks | G182: ONE_TO_ONE | H182: APPROVED | I182: New | J182: Source assignment -- not individually reviewed | N182: 10 EVIDENCE & DECISIONS
A183: Contractor Programme | B183: SCH-01-024 | C183: River crossing: utility relocation - release | D183: WBS Code = 1.1.2 | E183: R24-v1 | F183: 1.1.2 Guideway and Civil - Utility & Roadworks | G183: ONE_TO_ONE | H183: APPROVED | I183: New | J183: Source assignment -- not individually reviewed | N183: 10 EVIDENCE & DECISIONS
A184: Contractor Programme | B184: SCH-01-027 | C184: Depot lead: guideway pier reinforcement - inspection | D184: WBS Code = 1.1.2 | E184: R27-v1 | F184: 1.1.2 Guideway and Civil - Utility & Roadworks | G184: ONE_TO_ONE | H184: APPROVED | I184: New | J184: Source assignment -- not individually reviewed | N184: 10 EVIDENCE & DECISIONS
A185: Contractor Programme | B185: SCH-01-030 | C185: Central guideway: retaining-wall excavation - field start | D185: WBS Code = 1.1.2 | E185: R30-v1 | F185: 1.1.2 Guideway and Civil - Utility & Roadworks | G185: ONE_TO_ONE | H185: APPROVED | I185: New | J185: Source assignment -- not individually reviewed | N185: 10 EVIDENCE & DECISIONS
A186: Contractor Programme | B186: SCH-01-033 | C186: East portal: track-slab survey - turnover | D186: WBS Code = 1.1.2 | E186: R33-v1 | F186: 1.1.2 Guideway and Civil - Utility & Roadworks | G186: ONE_TO_ONE | H186: APPROVED | I186: New | J186: Source assignment -- not individually reviewed | N186: 10 EVIDENCE & DECISIONS
A187: Contractor Programme | B187: SCH-01-036 | C187: West approach: road restoration - installation | D187: WBS Code = 1.1.2 | E187: R36-v1 | F187: 1.1.2 Guideway and Civil - Utility & Roadworks | G187: ONE_TO_ONE | H187: APPROVED | I187: New | J187: Source assignment -- not individually reviewed | N187: 10 EVIDENCE & DECISIONS
... A235: Contractor Programme | B235: SCH-01-180 | C235: Central guideway: road restoration - field start | D235: WBS Code = 1.1.2 | E235: R180-v1 | F235: 1.1.2 Guideway and Civil - Utility & Roadworks | G235: ONE_TO_ONE | H235: APPROVED | I235: New | J235: Source assignment -- not individually reviewed | N235: 10 EVIDENCE & DECISIONS
A236: Cost & Forecast Control Accounts | B236: CST-01-002 | C236: Guideway and Civil - temporary works - allowance | D236: Cost Account = CA-1002; WBS Code = 1.1.2 | E236: R1084-v1 | F236: 1.1.2 Guideway and Civil - Utility & Roadworks | G236: ONE_TO_ONE | H236: APPROVED | I236: New | J236: Source assignment -- not individually reviewed | N236: 10 EVIDENCE & DECISIONS | O236: 365000 | P236: 377500 | Q236: CAD | S236: 2027-06-30 | T236: C1-R0 | U236: Supplied practice file monthly_cost_forecast.xlsx, row 3 | V236: Whole source account, not a target allocation. Repeated target rows must not be summed. Aggregate cost / forecast remains withheld.
A237: Cost & Forecast Control Accounts | B237: CST-01-004 | C237: Guideway and Civil - roadworks - field package | D237: Cost Account = CA-1004; WBS Code = 1.1.2 | E237: R1086-v1 | F237: 1.1.2 Guideway and Civil - Utility & Roadworks | G237: ONE_TO_ONE | H237: APPROVED | I237: New | J237: Source assignment -- not individually reviewed | N237: 10 EVIDENCE & DECISIONS | O237: 400000 | P237: 387500 | Q237: CAD | S237: 2027-06-30 | T237: C1-R0 | U237: Supplied practice file monthly_cost_forecast.xlsx, row 5 | V237: Whole source account, not a target allocation. Repeated target rows must not be summed. Aggregate cost / forecast remains withheld.
A238: Cost & Forecast Control Accounts | B238: CST-01-006 | C238: Guideway and Civil - concrete structures - professional services | D238: Cost Account = CA-1006; WBS Code = 1.1.2 | E238: R1088-v1 | F238: 1.1.2 Guideway and Civil - Utility & Roadworks | G238: ONE_TO_ONE | H238: APPROVED | I238: New | J238: Source assignment -- not individually reviewed | N238: 10 EVIDENCE & DECISIONS | O238: 435000 | P238: 447500 | Q238: CAD | S238: 2027-06-30 | T238: C1-R0 | U238: Supplied practice file monthly_cost_forecast.xlsx, row 7 | V238: Whole source account, not a target allocation. Repeated target rows must not be summed. Aggregate cost / forecast remains withheld.
A239: Cost & Forecast Control Accounts | B239: CST-01-008 | C239: Guideway and Civil - temporary works - closeout | D239: Cost Account = CA-1008; WBS Code = 1.1.2 | E239: R1090-v1 | F239: 1.1.2 Guideway and Civil - Utility & Roadworks | G239: ONE_TO_ONE | H239: APPROVED | I239: New | J239: Source assignment -- not individually reviewed | N239: 10 EVIDENCE & DECISIONS | O239: 470000 | P239: 457500 | Q239: CAD | S239: 2027-06-30 | T239: C1-R0 | U239: Supplied practice file monthly_cost_forecast.xlsx, row 9 | V239: Whole source account, not a target allocation. Repeated target rows must not be summed. Aggregate cost / forecast remains withheld.
A240: Cost & Forecast Control Accounts | B240: CST-01-010 | C240: Guideway and Civil - roadworks - supply and install | D240: Cost Account = CA-1010; WBS Code = 1.1.2 | E240: R1092-v1 | F240: 1.1.2 Guideway and Civil - Utility & Roadworks | G240: ONE_TO_ONE | H240: APPROVED | I240: New | J240: Source assignment -- not individually reviewed | N240: 10 EVIDENCE & DECISIONS | O240: 505000 | P240: 517500 | Q240: CAD | S240: 2027-06-30 | T240: C1-R0 | U240: Supplied practice file monthly_cost_forecast.xlsx, row 11 | V240: Whole source account, not a target allocation. Repeated target rows must not be summed. Aggregate cost / forecast remains withheld.
A241: Cost & Forecast Control Accounts | B241: CST-01-012 | C241: Guideway and Civil - concrete structures - allowance | D241: Cost Account = CA-1012; WBS Code = 1.1.2 | E241: R1094-v1 | F241: 1.1.2 Guideway and Civil - Utility & Roadworks | G241: ONE_TO_ONE | H241: APPROVED | I241: New | J241: Source assignment -- not individually reviewed | N241: 10 EVIDENCE & DECISIONS | O241: 540000 | P241: 527500 | Q241: CAD | S241: 2027-06-30 | T241: C1-R0 | U241: Supplied practice file monthly_cost_forecast.xlsx, row 13 | V241: Whole source account, not a target allocation. Repeated target rows must not be summed. Aggregate cost / forecast remains withheld.
A242: Cost & Forecast Control Accounts | B242: CST-01-014 | C242: Guideway and Civil - temporary works - field package | D242: Cost Account = CA-1014; WBS Code = 1.1.2 | E242: R1096-v1 | F242: 1.1.2 Guideway and Civil - Utility & Roadworks | G242: ONE_TO_ONE | H242: APPROVED | I242: New | J242: Source assignment -- not individually reviewed | N242: 10 EVIDENCE & DECISIONS | O242: 575000 | P242: 587500 | Q242: CAD | S242: 2027-06-30 | T242: C1-R0 | U242: Supplied practice file monthly_cost_forecast.xlsx, row 15 | V242: Whole source account, not a target allocation. Repeated target rows must not be summed. Aggregate cost / forecast remains withheld.
A243: Cost & Forecast Control Accounts | B243: CST-01-016 | C243: Guideway and Civil - roadworks - professional services | D243: Cost Account = CA-1016; WBS Code = 1.1.2 | E243: R1098-v1 | F243: 1.1.2 Guideway and Civil - Utility & Roadworks | G243: ONE_TO_ONE | H243: APPROVED | I243: New | J243: Source assignment -- not individually reviewed | N243: 10 EVIDENCE & DECISIONS | O243: 610000 | P243: 597500 | Q243: CAD | S243: 2027-06-30 | T243: C1-R0 | U243: Supplied practice file monthly_cost_forecast.xlsx, row 17 | V243: Whole source account, not a target allocation. Repeated target rows must not be summed. Aggregate cost / forecast remains withheld.
A244: Cost & Forecast Control Accounts | B244: CST-01-018 | C244: Guideway and Civil - concrete structures - closeout | D244: Cost Account = CA-1018; WBS Code = 1.1.2 | E244: R1100-v1 | F244: 1.1.2 Guideway and Civil - Utility & Roadworks | G244: ONE_TO_ONE | H244: APPROVED | I244: New | J244: Source assignment -- not individually reviewed | N244: 10 EVIDENCE & DECISIONS | O244: 645000 | P244: 657500 | Q244: CAD | S244: 2027-06-30 | T244: C1-R0 | U244: Supplied practice file monthly_cost_forecast.xlsx, row 19 | V244: Whole source account, not a target allocation. Repeated target rows must not be summed. Aggregate cost / forecast remains withheld.
A245: Cost & Forecast Control Accounts | B245: CST-01-020 | C245: Guideway and Civil - temporary works - supply and install | D245: Cost Account = CA-1020; WBS Code = 1.1.2 | E245: R1102-v1 | F245: 1.1.2 Guideway and Civil - Utility & Roadworks | G245: ONE_TO_ONE | H245: APPROVED | I245: New | J245: Source assignment -- not individually reviewed | N245: 10 EVIDENCE & DECISIONS | O245: 680000 | P245: 667500 | Q245: CAD | S245: 2027-06-30 | T245: C1-R0 | U245: Supplied practice file monthly_cost_forecast.xlsx, row 21 | V245: Whole source account, not a target allocation. Repeated target rows must not be summed. Aggregate cost / forecast remains withheld.
A246: Cost & Forecast Control Accounts | B246: CST-01-022 | C246: Guideway and Civil - roadworks - allowance | D246: Cost Account = CA-1022; WBS Code = 1.1.2 | E246: R1104-v1 | F246: 1.1.2 Guideway and Civil - Utility & Roadworks | G246: ONE_TO_ONE | H246: APPROVED | I246: New | J246: Source assignment -- not individually reviewed | N246: 10 EVIDENCE & DECISIONS | O246: 715000 | P246: 727500 | Q246: CAD | S246: 2027-06-30 | T246: C1-R0 | U246: Supplied practice file monthly_cost_forecast.xlsx, row 23 | V246: Whole source account, not a target allocation. Repeated target rows must not be summed. Aggregate cost / forecast remains withheld.
A247: Cost & Forecast Control Accounts | B247: CST-01-024 | C247: Guideway and Civil - concrete structures - field package | D247: Cost Account = CA-1024; WBS Code = 1.1.2 | E247: R1106-v1 | F247: 1.1.2 Guideway and Civil - Utility & Roadworks | G247: ONE_TO_ONE | H247: APPROVED | I247: New | J247: Source assignment -- not individually reviewed | N247: 10 EVIDENCE & DECISIONS | O247: 750000 | P247: 737500 | Q247: CAD | S247: 2027-06-30 | T247: C1-R0 | U247: Supplied practice file monthly_cost_forecast.xlsx, row 25 | V247: Whole source account, not a target allocation. Repeated target rows must not be summed. Aggregate cost / forecast remains withheld.
... A275: Cost & Forecast Control Accounts | B275: CST-01-080 | C275: Guideway and Civil - temporary works - supply and install | D275: Cost Account = CA-1080; WBS Code = 1.1.2 | E275: R1162-v1 | F275: 1.1.2 Guideway and Civil - Utility & Roadworks | G275: ONE_TO_ONE | H275: APPROVED | I275: New | J275: Source assignment -- not individually reviewed | N275: 10 EVIDENCE & DECISIONS | O275: 1730000 | P275: 1717500 | Q275: CAD | S275: 2027-06-30 | T275: C1-R0 | U275: Supplied practice file monthly_cost_forecast.xlsx, row 81 | V275: Whole source account, not a target allocation. Repeated target rows must not be summed. Aggregate cost / forecast remains withheld.
A276: Commercial Package Register | B276: PKG-001 | C276: Guideway Civil Works | D276: Package Code = PK-101; WBS Code = 1.1;1.2 | E276: R1563-v2 | F276: 1.2 Stations | G276: ONE_TO_MANY | H276: APPROVED | I276: New | J276: Professional decision | K276: Maya Chen, Owner Project Controls | M276: Source states 'WBS Code' = '1.1;1.2' -- names no element of this WBS -- professional reason (Maya Chen, Owner Project Controls): Source package register explicitly states both Owner-WBS branches. | N276: 10 EVIDENCE & DECISIONS
A277: Commercial Package Register | B277: PKG-011 | C277: Station Structural Works | D277: Package Code = PK-201; WBS Code = 1.2 | E277: R1573-v1 | F277: 1.2 Stations | G277: ONE_TO_ONE | H277: APPROVED | I277: New | J277: Source assignment -- not individually reviewed | N277: 10 EVIDENCE & DECISIONS
A278: Commercial Package Register | B278: PKG-012 | C278: Station Fit-Out | D278: Package Code = PK-202; WBS Code = 1.2 | E278: R1574-v1 | F278: 1.2 Stations | G278: ONE_TO_ONE | H278: APPROVED | I278: New | J278: Source assignment -- not individually reviewed | N278: 10 EVIDENCE & DECISIONS
A279: Commercial Package Register | B279: PKG-013 | C279: Building Services | D279: Package Code = PK-203; WBS Code = 1.2 | E279: R1575-v1 | F279: 1.2 Stations | G279: ONE_TO_ONE | H279: APPROVED | I279: New | J279: Source assignment -- not individually reviewed | N279: 10 EVIDENCE & DECISIONS
A280: Commercial Package Register | B280: PKG-014 | C280: Public Realm | D280: Package Code = PK-204; WBS Code = 1.2 | E280: R1576-v1 | F280: 1.2 Stations | G280: ONE_TO_ONE | H280: APPROVED | I280: New | J280: Source assignment -- not individually reviewed | N280: 10 EVIDENCE & DECISIONS
A281: Commercial Package Register | B281: PKG-015 | C281: Station Structural Works - Lot 2 | D281: Package Code = PK-205; WBS Code = 1.2 | E281: R1577-v1 | F281: 1.2 Stations | G281: ONE_TO_ONE | H281: APPROVED | I281: New | J281: Source assignment -- not individually reviewed | N281: 10 EVIDENCE & DECISIONS
A282: Commercial Package Register | B282: PKG-016 | C282: Station Fit-Out - Lot 2 | D282: Package Code = PK-206; WBS Code = 1.2 | E282: R1578-v1 | F282: 1.2 Stations | G282: ONE_TO_ONE | H282: APPROVED | I282: New | J282: Source assignment -- not individually reviewed | N282: 10 EVIDENCE & DECISIONS
A283: Commercial Package Register | B283: PKG-017 | C283: Building Services - Lot 2 | D283: Package Code = PK-207; WBS Code = 1.2 | E283: R1579-v1 | F283: 1.2 Stations | G283: ONE_TO_ONE | H283: APPROVED | I283: New | J283: Source assignment -- not individually reviewed | N283: 10 EVIDENCE & DECISIONS
A284: Commercial Package Register | B284: PKG-018 | C284: Public Realm - Lot 2 | D284: Package Code = PK-208; WBS Code = 1.2 | E284: R1580-v1 | F284: 1.2 Stations | G284: ONE_TO_ONE | H284: APPROVED | I284: New | J284: Source assignment -- not individually reviewed | N284: 10 EVIDENCE & DECISIONS
A285: Commercial Package Register | B285: PKG-019 | C285: Station Structural Works - Lot 3 | D285: Package Code = PK-209; WBS Code = 1.2 | E285: R1581-v1 | F285: 1.2 Stations | G285: ONE_TO_ONE | H285: APPROVED | I285: New | J285: Source assignment -- not individually reviewed | N285: 10 EVIDENCE & DECISIONS
A286: Commercial Package Register | B286: PKG-020 | C286: Station Fit-Out - Lot 3 | D286: Package Code = PK-210; WBS Code = 1.2 | E286: R1582-v1 | F286: 1.2 Stations | G286: ONE_TO_ONE | H286: APPROVED | I286: New | J286: Source assignment -- not individually reviewed | N286: 10 EVIDENCE & DECISIONS
A287: Contractor Programme | B287: SCH-02-001 | C287: Harbour Station: vertical-transport installation - inspection | D287: WBS Code = 1.2.1 | E287: R181-v1 | F287: 1.2.1 Stations - Station Structures | G287: ONE_TO_ONE | H287: APPROVED | I287: New | J287: Source assignment -- not individually reviewed | N287: 10 EVIDENCE & DECISIONS
A288: Contractor Programme | B288: SCH-02-002 | C288: Market Station: platform edge installation - turnover | D288: WBS Code = 1.2.1 | E288: R182-v1 | F288: 1.2.1 Stations - Station Structures | G288: ONE_TO_ONE | H288: APPROVED | I288: New | J288: Source assignment -- not individually reviewed | N288: 10 EVIDENCE & DECISIONS
... A406: Contractor Programme | B406: SCH-02-179 | C406: University Station: architectural wall framing - field start | D406: WBS Code = 1.2.1 | E406: R359-v1 | F406: 1.2.1 Stations - Station Structures | G406: ONE_TO_ONE | H406: APPROVED | I406: New | J406: Source assignment -- not individually reviewed | N406: 10 EVIDENCE & DECISIONS
A407: Cost & Forecast Control Accounts | B407: CST-02-001 | C407: Stations - public realm - allowance | D407: Cost Account = CA-2001; WBS Code = 1.2.1 | E407: R1163-v1 | F407: 1.2.1 Stations - Station Structures | G407: ONE_TO_ONE | H407: APPROVED | I407: New | J407: Source assignment -- not individually reviewed | N407: 10 EVIDENCE & DECISIONS | O407: 427500 | P407: 427500 | Q407: CAD | S407: 2027-06-30 | T407: C1-R0 | U407: Supplied practice file monthly_cost_forecast.xlsx, row 82 | V407: Whole source account, not a target allocation. Repeated target rows must not be summed. Aggregate cost / forecast remains withheld.
A408: Cost & Forecast Control Accounts | B408: CST-02-003 | C408: Stations - building services - field package | D408: Cost Account = CA-2003; WBS Code = 1.2.1 | E408: R1165-v1 | F408: 1.2.1 Stations - Station Structures | G408: ONE_TO_ONE | H408: APPROVED | I408: New | J408: Source assignment -- not individually reviewed | N408: 10 EVIDENCE & DECISIONS | O408: 462500 | P408: 487500 | Q408: CAD | S408: 2027-06-30 | T408: C1-R0 | U408: Supplied practice file monthly_cost_forecast.xlsx, row 84 | V408: Whole source account, not a target allocation. Repeated target rows must not be summed. Aggregate cost / forecast remains withheld.
A409: Cost & Forecast Control Accounts | B409: CST-02-005 | C409: Stations - station structure - professional services | D409: Cost Account = CA-2005; WBS Code = 1.2.1 | E409: R1167-v1 | F409: 1.2.1 Stations - Station Structures | G409: ONE_TO_ONE | H409: APPROVED | I409: New | J409: Source assignment -- not individually reviewed | N409: 10 EVIDENCE & DECISIONS | O409: 497500 | P409: 497500 | Q409: CAD | S409: 2027-06-30 | T409: C1-R0 | U409: Supplied practice file monthly_cost_forecast.xlsx, row 86 | V409: Whole source account, not a target allocation. Repeated target rows must not be summed. Aggregate cost / forecast remains withheld.
A410: Cost & Forecast Control Accounts | B410: CST-02-007 | C410: Stations - public realm - closeout | D410: Cost Account = CA-2007; WBS Code = 1.2.1 | E410: R1169-v1 | F410: 1.2.1 Stations - Station Structures | G410: ONE_TO_ONE | H410: APPROVED | I410: New | J410: Source assignment -- not individually reviewed | N410: 10 EVIDENCE & DECISIONS | O410: 532500 | P410: 557500 | Q410: CAD | S410: 2027-06-30 | T410: C1-R0 | U410: Supplied practice file monthly_cost_forecast.xlsx, row 88 | V410: Whole source account, not a target allocation. Repeated target rows must not be summed. Aggregate cost / forecast remains withheld.
A411: Cost & Forecast Control Accounts | B411: CST-02-009 | C411: Stations - building services - supply and install | D411: Cost Account = CA-2009; WBS Code = 1.2.1 | E411: R1171-v1 | F411: 1.2.1 Stations - Station Structures | G411: ONE_TO_ONE | H411: APPROVED | I411: New | J411: Source assignment -- not individually reviewed | N411: 10 EVIDENCE & DECISIONS | O411: 567500 | P411: 567500 | Q411: CAD | S411: 2027-06-30 | T411: C1-R0 | U411: Supplied practice file monthly_cost_forecast.xlsx, row 90 | V411: Whole source account, not a target allocation. Repeated target rows must not be summed. Aggregate cost / forecast remains withheld.
A412: Cost & Forecast Control Accounts | B412: CST-02-011 | C412: Stations - station structure - allowance | D412: Cost Account = CA-2011; WBS Code = 1.2.1 | E412: R1173-v1 | F412: 1.2.1 Stations - Station Structures | G412: ONE_TO_ONE | H412: APPROVED | I412: New | J412: Source assignment -- not individually reviewed | N412: 10 EVIDENCE & DECISIONS | O412: 602500 | P412: 627500 | Q412: CAD | S412: 2027-06-30 | T412: C1-R0 | U412: Supplied practice file monthly_cost_forecast.xlsx, row 92 | V412: Whole source account, not a target allocation. Repeated target rows must not be summed. Aggregate cost / forecast remains withheld.
A413: Cost & Forecast Control Accounts | B413: CST-02-013 | C413: Stations - public realm - field package | D413: Cost Account = CA-2013; WBS Code = 1.2.1 | E413: R1175-v1 | F413: 1.2.1 Stations - Station Structures | G413: ONE_TO_ONE | H413: APPROVED | I413: New | J413: Source assignment -- not individually reviewed | N413: 10 EVIDENCE & DECISIONS | O413: 637500 | P413: 637500 | Q413: CAD | S413: 2027-06-30 | T413: C1-R0 | U413: Supplied practice file monthly_cost_forecast.xlsx, row 94 | V413: Whole source account, not a target allocation. Repeated target rows must not be summed. Aggregate cost / forecast remains withheld.
A414: Cost & Forecast Control Accounts | B414: CST-02-015 | C414: Stations - building services - professional services | D414: Cost Account = CA-2015; WBS Code = 1.2.1 | E414: R1177-v1 | F414: 1.2.1 Stations - Station Structures | G414: ONE_TO_ONE | H414: APPROVED | I414: New | J414: Source assignment -- not individually reviewed | N414: 10 EVIDENCE & DECISIONS | O414: 672500 | P414: 697500 | Q414: CAD | S414: 2027-06-30 | T414: C1-R0 | U414: Supplied practice file monthly_cost_forecast.xlsx, row 96 | V414: Whole source account, not a target allocation. Repeated target rows must not be summed. Aggregate cost / forecast remains withheld.
A415: Cost & Forecast Control Accounts | B415: CST-02-017 | C415: Stations - station structure - closeout | D415: Cost Account = CA-2017; WBS Code = 1.2.1 | E415: R1179-v1 | F415: 1.2.1 Stations - Station Structures | G415: ONE_TO_ONE | H415: APPROVED | I415: New | J415: Source assignment -- not individually reviewed | N415: 10 EVIDENCE & DECISIONS | O415: 707500 | P415: 707500 | Q415: CAD | S415: 2027-06-30 | T415: C1-R0 | U415: Supplied practice file monthly_cost_forecast.xlsx, row 98 | V415: Whole source account, not a target allocation. Repeated target rows must not be summed. Aggregate cost / forecast remains withheld.
A416: Cost & Forecast Control Accounts | B416: CST-02-019 | C416: Stations - public realm - supply and install | D416: Cost Account = CA-2019; WBS Code = 1.2.1 | E416: R1181-v1 | F416: 1.2.1 Stations - Station Structures | G416: ONE_TO_ONE | H416: APPROVED | I416: New | J416: Source assignment -- not individually reviewed | N416: 10 EVIDENCE & DECISIONS | O416: 742500 | P416: 767500 | Q416: CAD | S416: 2027-06-30 | T416: C1-R0 | U416: Supplied practice file monthly_cost_forecast.xlsx, row 100 | V416: Whole source account, not a target allocation. Repeated target rows must not be summed. Aggregate cost / forecast remains withheld.
A417: Cost & Forecast Control Accounts | B417: CST-02-021 | C417: Stations - building services - allowance | D417: Cost Account = CA-2021; WBS Code = 1.2.1 | E417: R1183-v1 | F417: 1.2.1 Stations - Station Structures | G417: ONE_TO_ONE | H417: APPROVED | I417: New | J417: Source assignment -- not individually reviewed | N417: 10 EVIDENCE & DECISIONS | O417: 777500 | P417: 777500 | Q417: CAD | S417: 2027-06-30 | T417: C1-R0 | U417: Supplied practice file monthly_cost_forecast.xlsx, row 102 | V417: Whole source account, not a target allocation. Repeated target rows must not be summed. Aggregate cost / forecast remains withheld.
A418: Cost & Forecast Control Accounts | B418: CST-02-023 | C418: Stations - station structure - field package | D418: Cost Account = CA-2023; WBS Code = 1.2.1 | E418: R1185-v1 | F418: 1.2.1 Stations - Station Structures | G418: ONE_TO_ONE | H418: APPROVED | I418: New | J418: Source assignment -- not individually reviewed | N418: 10 EVIDENCE & DECISIONS | O418: 812500 | P418: 837500 | Q418: CAD | S418: 2027-06-30 | T418: C1-R0 | U418: Supplied practice file monthly_cost_forecast.xlsx, row 104 | V418: Whole source account, not a target allocation. Repeated target rows must not be summed. Aggregate cost / forecast remains withheld.
... A446: Cost & Forecast Control Accounts | B446: CST-02-079 | C446: Stations - public realm - supply and install | D446: Cost Account = CA-2079; WBS Code = 1.2.1 | E446: R1241-v1 | F446: 1.2.1 Stations - Station Structures | G446: ONE_TO_ONE | H446: APPROVED | I446: New | J446: Source assignment -- not individually reviewed | N446: 10 EVIDENCE & DECISIONS | O446: 1792500 | P446: 1817500 | Q446: CAD | S446: 2027-06-30 | T446: C1-R0 | U446: Supplied practice file monthly_cost_forecast.xlsx, row 160 | V446: Whole source account, not a target allocation. Repeated target rows must not be summed. Aggregate cost / forecast remains withheld.
A447: Contractor Programme | B447: SCH-02-006 | C447: Harbour Station: station ventilation rough-in - inspection | D447: WBS Code = 1.2.2 | E447: R186-v1 | F447: 1.2.2 Stations - Architectural Fit-Out | G447: ONE_TO_ONE | H447: APPROVED | I447: New | J447: Source assignment -- not individually reviewed | N447: 10 EVIDENCE & DECISIONS
A448: Contractor Programme | B448: SCH-02-009 | C448: University Station: vertical-transport installation - field start | D448: WBS Code = 1.2.2 | E448: R189-v1 | F448: 1.2.2 Stations - Architectural Fit-Out | G448: ONE_TO_ONE | H448: APPROVED | I448: New | J448: Source assignment -- not individually reviewed | N448: 10 EVIDENCE & DECISIONS
A449: Contractor Programme | B449: SCH-02-012 | C449: Market Station: fire-life-safety cabling - turnover | D449: WBS Code = 1.2.2 | E449: R192-v1 | F449: 1.2.2 Stations - Architectural Fit-Out | G449: ONE_TO_ONE | H449: APPROVED | I449: New | J449: Source assignment -- not individually reviewed | N449: 10 EVIDENCE & DECISIONS
A450: Contractor Programme | B450: SCH-02-015 | C450: West Terminal: public-realm paving - installation | D450: WBS Code = 1.2.2 | E450: R195-v1 | F450: 1.2.2 Stations - Architectural Fit-Out | G450: ONE_TO_ONE | H450: APPROVED | I450: New | J450: Source assignment -- not individually reviewed | N450: 10 EVIDENCE & DECISIONS
A451: Contractor Programme | B451: SCH-02-018 | C451: Civic Station: platform edge installation - release | D451: WBS Code = 1.2.2 | E451: R198-v1 | F451: 1.2.2 Stations - Architectural Fit-Out | G451: ONE_TO_ONE | H451: APPROVED | I451: New | J451: Source assignment -- not individually reviewed | N451: 10 EVIDENCE & DECISIONS
A452: Contractor Programme | B452: SCH-02-021 | C452: Harbour Station: concourse slab pour - inspection | D452: WBS Code = 1.2.2 | E452: R201-v1 | F452: 1.2.2 Stations - Architectural Fit-Out | G452: ONE_TO_ONE | H452: APPROVED | I452: New | J452: Source assignment -- not individually reviewed | N452: 10 EVIDENCE & DECISIONS
A453: Contractor Programme | B453: SCH-02-024 | C453: University Station: entrance steel erection - field start | D453: WBS Code = 1.2.2 | E453: R204-v1 | F453: 1.2.2 Stations - Architectural Fit-Out | G453: ONE_TO_ONE | H453: APPROVED | I453: New | J453: Source assignment -- not individually reviewed | N453: 10 EVIDENCE & DECISIONS
A454: Contractor Programme | B454: SCH-02-027 | C454: Market Station: architectural wall framing - turnover | D454: WBS Code = 1.2.2 | E454: R207-v1 | F454: 1.2.2 Stations - Architectural Fit-Out | G454: ONE_TO_ONE | H454: APPROVED | I454: New | J454: Source assignment -- not individually reviewed | N454: 10 EVIDENCE & DECISIONS
A455: Contractor Programme | B455: SCH-02-030 | C455: West Terminal: station ventilation rough-in - installation | D455: WBS Code = 1.2.2 | E455: R210-v1 | F455: 1.2.2 Stations - Architectural Fit-Out | G455: ONE_TO_ONE | H455: APPROVED | I455: New | J455: Source assignment -- not individually reviewed | N455: 10 EVIDENCE & DECISIONS
A456: Contractor Programme | B456: SCH-02-033 | C456: Civic Station: vertical-transport installation - release | D456: WBS Code = 1.2.2 | E456: R213-v1 | F456: 1.2.2 Stations - Architectural Fit-Out | G456: ONE_TO_ONE | H456: APPROVED | I456: New | J456: Source assignment -- not individually reviewed | N456: 10 EVIDENCE & DECISIONS
A457: Contractor Programme | B457: SCH-02-036 | C457: Harbour Station: fire-life-safety cabling - inspection | D457: WBS Code = 1.2.2 | E457: R216-v1 | F457: 1.2.2 Stations - Architectural Fit-Out | G457: ONE_TO_ONE | H457: APPROVED | I457: New | J457: Source assignment -- not individually reviewed | N457: 10 EVIDENCE & DECISIONS
A458: Contractor Programme | B458: SCH-02-039 | C458: University Station: public-realm paving - field start | D458: WBS Code = 1.2.2 | E458: R219-v1 | F458: 1.2.2 Stations - Architectural Fit-Out | G458: ONE_TO_ONE | H458: APPROVED | I458: New | J458: Source assignment -- not individually reviewed | N458: 10 EVIDENCE & DECISIONS
... A505: Contractor Programme | B505: SCH-02-180 | C505: West Terminal: fire-life-safety cabling - installation | D505: WBS Code = 1.2.2 | E505: R360-v1 | F505: 1.2.2 Stations - Architectural Fit-Out | G505: ONE_TO_ONE | H505: APPROVED | I505: New | J505: Source assignment -- not individually reviewed | N505: 10 EVIDENCE & DECISIONS
A506: Cost & Forecast Control Accounts | B506: CST-02-002 | C506: Stations - station structure - closeout | D506: Cost Account = CA-2002; WBS Code = 1.2.2 | E506: R1164-v1 | F506: 1.2.2 Stations - Architectural Fit-Out | G506: ONE_TO_ONE | H506: APPROVED | I506: New | J506: Source assignment -- not individually reviewed | N506: 10 EVIDENCE & DECISIONS | O506: 445000 | P506: 457500 | Q506: CAD | S506: 2027-06-30 | T506: C1-R0 | U506: Supplied practice file monthly_cost_forecast.xlsx, row 83 | V506: Whole source account, not a target allocation. Repeated target rows must not be summed. Aggregate cost / forecast remains withheld.
A507: Cost & Forecast Control Accounts | B507: CST-02-004 | C507: Stations - public realm - supply and install | D507: Cost Account = CA-2004; WBS Code = 1.2.2 | E507: R1166-v1 | F507: 1.2.2 Stations - Architectural Fit-Out | G507: ONE_TO_ONE | H507: APPROVED | I507: New | J507: Source assignment -- not individually reviewed | N507: 10 EVIDENCE & DECISIONS | O507: 480000 | P507: 467500 | Q507: CAD | S507: 2027-06-30 | T507: C1-R0 | U507: Supplied practice file monthly_cost_forecast.xlsx, row 85 | V507: Whole source account, not a target allocation. Repeated target rows must not be summed. Aggregate cost / forecast remains withheld.
A508: Cost & Forecast Control Accounts | B508: CST-02-006 | C508: Stations - building services - allowance | D508: Cost Account = CA-2006; WBS Code = 1.2.2 | E508: R1168-v1 | F508: 1.2.2 Stations - Architectural Fit-Out | G508: ONE_TO_ONE | H508: APPROVED | I508: New | J508: Source assignment -- not individually reviewed | N508: 10 EVIDENCE & DECISIONS | O508: 515000 | P508: 527500 | Q508: CAD | S508: 2027-06-30 | T508: C1-R0 | U508: Supplied practice file monthly_cost_forecast.xlsx, row 87 | V508: Whole source account, not a target allocation. Repeated target rows must not be summed. Aggregate cost / forecast remains withheld.
...

Sheet 09 WBS EXPLORER
A1: WBS EXPLORER
A2: The approved WBS as integration spine, with governed relationship populations beneath it.
A3: Executive | B3: Issues | C3: Integration | D3: Project | E3: Changes | F3: Crosswalk | G3: Evidence | H3: Sources
A4: Governed relationship coverage/status → advanced approved scope / relationship-row view
A5: WBS | B5: Element | C5: Level | D5: Schedule | E5: Cost / forecast | F5: Package / contract | G5: Other | H5: Open / unresolved | I5: Changed | J5: Integration condition | K5: Crosswalk
B6: HarbourLink Urban Transit Expansion | C6: 0 | D6: 898 governed relationships | E6: 399 governed relationships | F6: 60 governed relationships | G6: 0 governed relationships | H6: 0 | I6: 1357 | J6: Aligned: Schedule and cost both relate through this WBS branch. 60 package/contract relationships also project through this branch. | K6: 08 CROSSWALK
A7: 1 | B7: HarbourLink Urban Transit Expansion | C7: 1 | D7: 898 governed relationships | E7: 399 governed relationships | F7: 60 governed relationships | G7: 0 governed relationships | H7: 0 | I7: 1357 | J7: Aligned: Schedule and cost both relate through this WBS branch. 60 package/contract relationships also project through this branch. | K7: 08 CROSSWALK
A8: 1.1 | B8: Guideway and Civil | C8: 2 | D8: 180 governed relationships | E8: 80 governed relationships | F8: 10 governed relationships | G8: 0 governed relationships | H8: 0 | I8: 270 | J8: Aligned: Schedule and cost both relate through this WBS branch. 10 package/contract relationships also project through this branch. | K8: 08 CROSSWALK
A9: 1.1.1 | B9: Guideway and Civil - Guideway Structures | C9: 3 | D9: 120 governed relationships | E9: 40 governed relationships | F9: 0 governed relationships | G9: 0 governed relationships | H9: 0 | I9: 160 | J9: Aligned: Schedule and cost both relate through this WBS branch. | K9: 08 CROSSWALK
A10: 1.1.1.1 | B10: Guideway Structures - East Segment | C10: 4 | D10: 0 governed relationships | E10: 0 governed relationships | F10: 0 governed relationships | G10: 0 governed relationships | H10: 0 | I10: 0 | J10: Partial: No governed schedule or cost relationships in this WBS branch. | K10: 08 CROSSWALK
A11: 1.1.1.2 | B11: Guideway Structures - West Segment | C11: 4 | D11: 0 governed relationships | E11: 0 governed relationships | F11: 0 governed relationships | G11: 0 governed relationships | H11: 0 | I11: 0 | J11: Partial: No governed schedule or cost relationships in this WBS branch. | K11: 08 CROSSWALK
A12: 1.1.2 | B12: Guideway and Civil - Utility & Roadworks | C12: 3 | D12: 60 governed relationships | E12: 40 governed relationships | F12: 0 governed relationships | G12: 0 governed relationships | H12: 0 | I12: 100 | J12: Aligned: Schedule and cost both relate through this WBS branch. | K12: 08 CROSSWALK
A13: 1.1.2.1 | B13: Utility & Roadworks - East Segment | C13: 4 | D13: 0 governed relationships | E13: 0 governed relationships | F13: 0 governed relationships | G13: 0 governed relationships | H13: 0 | I13: 0 | J13: Partial: No governed schedule or cost relationships in this WBS branch. | K13: 08 CROSSWALK
A14: 1.1.2.2 | B14: Utility & Roadworks - West Segment | C14: 4 | D14: 0 governed relationships | E14: 0 governed relationships | F14: 0 governed relationships | G14: 0 governed relationships | H14: 0 | I14: 0 | J14: Partial: No governed schedule or cost relationships in this WBS branch. | K14: 08 CROSSWALK
A15: 1.1.3 | B15: Guideway and Civil - Track Support Works | C15: 3 | D15: 0 governed relationships | E15: 0 governed relationships | F15: 0 governed relationships | G15: 0 governed relationships | H15: 0 | I15: 0 | J15: Partial: No governed schedule or cost relationships in this WBS branch. | K15: 08 CROSSWALK
A16: 1.1.3.1 | B16: Track Support Works - East Segment | C16: 4 | D16: 0 governed relationships | E16: 0 governed relationships | F16: 0 governed relationships | G16: 0 governed relationships | H16: 0 | I16: 0 | J16: Partial: No governed schedule or cost relationships in this WBS branch. | K16: 08 CROSSWALK
A17: 1.1.3.2 | B17: Track Support Works - West Segment | C17: 4 | D17: 0 governed relationships | E17: 0 governed relationships | F17: 0 governed relationships | G17: 0 governed relationships | H17: 0 | I17: 0 | J17: Partial: No governed schedule or cost relationships in this WBS branch. | K17: 08 CROSSWALK
A18: 1.1.4 | B18: Guideway and Civil - Civil Interfaces | C18: 3 | D18: 0 governed relationships | E18: 0 governed relationships | F18: 0 governed relationships | G18: 0 governed relationships | H18: 0 | I18: 0 | J18: Partial: No governed schedule or cost relationships in this WBS branch. | K18: 08 CROSSWALK
... A85: 1.6.4.2 | B85: Delivery Integration - Delivery Partners | C85: 4 | D85: 0 governed relationships | E85: 0 governed relationships | F85: 0 governed relationships | G85: 0 governed relationships | H85: 0 | I85: 0 | J85: Partial: No governed schedule or cost relationships in this WBS branch. | K85: 08 CROSSWALK

Sheet 10 EVIDENCE & DECISIONS
A1: EVIDENCE & DECISIONS
A2: Source says → relationship / interpretation → professional decision → current governed state.
A3: Executive | B3: Issues | C3: Integration | D3: Project | E3: Changes | F3: Crosswalk | G3: Evidence | H3: Sources
A5: Relationship | B5: Source / record | C5: SOURCE SAYS | D5: RELATIONSHIP / INTERPRETATION | E5: Contrary / competing evidence | F5: PROFESSIONAL DECISION | G5: Decision scope | H5: CURRENT GOVERNED STATE | I5: Change / reopen | J5: Crosswalk
A6: R1563-v2 | B6: Commercial Package Register / PKG-001 | C6: Package Code = PK-101; WBS Code = 1.1;1.2 | D6: Proposed by Professional; target 1.1 Guideway and Civil | E6: Source states 'WBS Code' = '1.1;1.2' -- names no element of this WBS -- professional reason (Maya Chen, Owner Project Controls): Source package register explicitly states both Owner-WBS branches. | F6: Maya Chen, Owner Project Controls: Professional decision | G6: Individual | H6: APPROVED / ONE_TO_MANY; | I6: New | J6: 08 CROSSWALK
A7: R1564-v1 | B7: Commercial Package Register / PKG-002 | C7: Package Code = PK-102; WBS Code = 1.1 | D7: Proposed by Source assignment; target 1.1 Guideway and Civil | E7: None recorded | F7: No individual professional decision recorded; Source assignment -- not individually reviewed | G7: Not individually decided | H7: APPROVED / ONE_TO_ONE; | I7: New | J7: 08 CROSSWALK
A8: R1565-v1 | B8: Commercial Package Register / PKG-003 | C8: Package Code = PK-103; WBS Code = 1.1 | D8: Proposed by Source assignment; target 1.1 Guideway and Civil | E8: None recorded | F8: No individual professional decision recorded; Source assignment -- not individually reviewed | G8: Not individually decided | H8: APPROVED / ONE_TO_ONE; | I8: New | J8: 08 CROSSWALK
A9: R1566-v1 | B9: Commercial Package Register / PKG-004 | C9: Package Code = PK-104; WBS Code = 1.1 | D9: Proposed by Source assignment; target 1.1 Guideway and Civil | E9: None recorded | F9: No individual professional decision recorded; Source assignment -- not individually reviewed | G9: Not individually decided | H9: APPROVED / ONE_TO_ONE; | I9: New | J9: 08 CROSSWALK
A10: R1567-v1 | B10: Commercial Package Register / PKG-005 | C10: Package Code = PK-105; WBS Code = 1.1 | D10: Proposed by Source assignment; target 1.1 Guideway and Civil | E10: None recorded | F10: No individual professional decision recorded; Source assignment -- not individually reviewed | G10: Not individually decided | H10: APPROVED / ONE_TO_ONE; | I10: New | J10: 08 CROSSWALK
A11: R1568-v1 | B11: Commercial Package Register / PKG-006 | C11: Package Code = PK-106; WBS Code = 1.1 | D11: Proposed by Source assignment; target 1.1 Guideway and Civil | E11: None recorded | F11: No individual professional decision recorded; Source assignment -- not individually reviewed | G11: Not individually decided | H11: APPROVED / ONE_TO_ONE; | I11: New | J11: 08 CROSSWALK
A12: R1569-v1 | B12: Commercial Package Register / PKG-007 | C12: Package Code = PK-107; WBS Code = 1.1 | D12: Proposed by Source assignment; target 1.1 Guideway and Civil | E12: None recorded | F12: No individual professional decision recorded; Source assignment -- not individually reviewed | G12: Not individually decided | H12: APPROVED / ONE_TO_ONE; | I12: New | J12: 08 CROSSWALK
A13: R1570-v1 | B13: Commercial Package Register / PKG-008 | C13: Package Code = PK-108; WBS Code = 1.1 | D13: Proposed by Source assignment; target 1.1 Guideway and Civil | E13: None recorded | F13: No individual professional decision recorded; Source assignment -- not individually reviewed | G13: Not individually decided | H13: APPROVED / ONE_TO_ONE; | I13: New | J13: 08 CROSSWALK
A14: R1571-v1 | B14: Commercial Package Register / PKG-009 | C14: Package Code = PK-109; WBS Code = 1.1 | D14: Proposed by Source assignment; target 1.1 Guideway and Civil | E14: None recorded | F14: No individual professional decision recorded; Source assignment -- not individually reviewed | G14: Not individually decided | H14: APPROVED / ONE_TO_ONE; | I14: New | J14: 08 CROSSWALK
A15: R1572-v1 | B15: Commercial Package Register / PKG-010 | C15: Package Code = PK-110; WBS Code = 1.1 | D15: Proposed by Source assignment; target 1.1 Guideway and Civil | E15: None recorded | F15: No individual professional decision recorded; Source assignment -- not individually reviewed | G15: Not individually decided | H15: APPROVED / ONE_TO_ONE; | I15: New | J15: 08 CROSSWALK
A16: R1-v1 | B16: Contractor Programme / SCH-01-001 | C16: WBS Code = 1.1.1 | D16: Proposed by Source assignment; target 1.1.1 Guideway and Civil - Guideway Structures | E16: None recorded | F16: No individual professional decision recorded; Source assignment -- not individually reviewed | G16: Not individually decided | H16: APPROVED / ONE_TO_ONE; | I16: New | J16: 08 CROSSWALK
... A1628: R1482-v2 | B1628: Cost & Forecast Control Accounts / CST-05-080 | C1628: Cost Account = CA-5080 | D1628: Proposed by Professional; target UNSURE | E1628: None recorded | F1628: Maya Chen, Owner Project Controls: Professional decision | G1628: Group decision (81 records sharing one decision state) | H1628: APPROVED / UNSURE; | I1628: New | J1628: 08 CROSSWALK

Sheet 11 SOURCES & PROVENANCE
A1: SOURCES & PROVENANCE | O1: Advanced original field values
A2: The information boundary of this workbook. Supplied evidence is not the same as established interpretation.
A3: Executive | B3: Issues | C3: Integration | D3: Project | E3: Changes | F3: Crosswalk | G3: Evidence | H3: Sources | O3: B8 | P3: WORK_PACKAGE_LIST
O4: I8 | P4: TABLE
A5: Project source-representation integrity | B5: Established | O5: L8 | P5: SOURCE_REPRESENTATION_ESTABLISHED
O6: I9 | P6: TABLE
A7: Source | B7: Governed role | C7: Revision | D7: Reporting period | E7: Rows | F7: Role basis | G7: Role validity | H7: Table boundary | I7: Interpretation | J7: Interpretation basis | K7: Format | L7: File integrity | O7: J9 | P7: DETERMINISTIC_SEMANTIC_RELATION
A8: Commercial Package Register | B8: Work package register | C8: Rev 0 | D8: Initial | E8: 60 | F8: declared at upload | G8: AS_SUPPLIED | H8: ESTABLISHED | I8: Source table | J8: SOURCE_NATIVE_SCHEMA | K8: xlsx | L8: Source interpretation recorded | O8: L9 | P8: SOURCE_REPRESENTATION_ESTABLISHED
A9: Contractor Programme | B9: SCHEDULE | C9: Rev 0 | D9: Initial | E9: 1082 | F9: declared at upload | G9: AS_SUPPLIED | H9: ESTABLISHED | I9: Source table | J9: Evidence-based relationship interpretation | K9: csv | L9: Source interpretation recorded | O9: I10 | P9: TABLE
A10: Cost & Forecast Control Accounts | B10: COST_ESTIMATE | C10: Rev 0 | D10: Initial | E10: 480 | F10: declared at upload | G10: AS_SUPPLIED | H10: ESTABLISHED | I10: Source table | J10: Evidence-based relationship interpretation | K10: xlsx | L10: Source interpretation recorded | O10: J10 | P10: DETERMINISTIC_SEMANTIC_RELATION
A11: Owner WBS | B11: WBS_DICTIONARY | C11: Rev 0 | D11: Initial | E11: 79 | F11: declared at upload | G11: AS_SUPPLIED | H11: ESTABLISHED | I11: Source table | J11: Evidence-based relationship interpretation | K11: xlsx | L11: Source interpretation recorded | O11: L10 | P11: SOURCE_REPRESENTATION_ESTABLISHED
O12: I11 | P12: TABLE
O13: J11 | P13: DETERMINISTIC_SEMANTIC_RELATION
O14: L11 | P14: SOURCE_REPRESENTATION_ESTABLISHED

Sheet 12 ASSURANCE
A1: ASSURANCE | O1: Advanced original field values
A2: Exact governance detail and output boundaries. This sheet supports review; it does not create authority.
A3: Executive | B3: Issues | C3: Integration | D3: Project | E3: Changes | F3: Crosswalk | G3: Evidence | H3: Sources | O3: B12 | P3: SOURCE_REPRESENTATION_ESTABLISHED
A5: Assurance item | B5: Recorded value
A6: Workbook template edition | B6: Premium Workbook Rev 2
A7: Project | B7: HarbourLink Urban Transit Expansion
A8: Approved output identity | B8: Approved version 1 · stable mapping reference MV-1 · APPROVED
A9: Approved by | B9: Maya Chen, Owner Project Controls
A10: Approved timestamp | B10: 2026-10-16 14:11 UTC
A11: WBS version | B11: 1
A12: Source-representation integrity | B12: Source interpretation recorded
A13: Source-integrity unresolved count | B13: 0
A14: Relationship rows | B14: 1623
A15: Generation timestamp | B15: 2026-10-17 18:35 UTC
A17: Interpretation boundary
A18: Workbook/App/JSON/PDF agreement can prove that outputs consume one governed state. It cannot prove that an upstream source interpretation is true. Source representation integrity is a separate prerequisite for substantive management claims.
A21: Known output limitations
A22: • Management amount/date/duration measures are withheld unless field semantics are explicitly governed for that use.
A23: • The workbook projects independent source structures through governed WBS relationships; it does not create direct source-to-source truth.
A24: • Sheet 04 (issues for review) is not a ranked list and does not claim objective materiality without a governed ranking basis.
A25: • Fictional evaluation case. No real-client provenance, privacy/security/compliance or hosting-residency claim is made by this workbook.
A27: Visual / metric ledger
A28: ID | B28: Title | C28: Management question | D28: Basis / population | E28: Unresolved treatment | F28: Transformation | G28: Drill path | H28: Records | I28: Status
A29: V1 | B29: WBS × control-view integration matrix | C29: Which supplied project-control views have governed relationships through each major Owner-WBS branch? | D29: Latest approved MappingVersion and its approved source-role basis. | Non-retired governed/open relationship population scoped through each displayed WBS branch. | E29: Unresolved is distinct from assessed zero coverage and source-not-supplied. | F29: Categorical state from supplied source role plus branch-scoped governed/open relationships; no health percentage. | G29: visual → WBS branch → integrated project → Crosswalk → evidence/professional decision | H29: 1357 | I29: AVAILABLE
A30: V2 | B30: Management-attention concentration by WBS branch | C30: Where are governed reopened, unresolved or contradictory relationship populations concentrated? | D30: Latest approved relationship state and retained relationship evidence. | Branch-scoped relationships with reopened/unresolved/contradictory evidence. | E30: Counts remain explicit; no record-count-to-materiality inference. | F30: Count qualifying relationship records by approved WBS branch; overlapping categories remain separately labelled. | G30: visual → WBS branch → Changes/What Matters Now → Crosswalk → evidence | H30: 2 | I30: AVAILABLE
A31: V3 | B31: Cycle governed-state composition | C31: How much relationship state carried forward versus required revalidation/redecision/new/retired treatment? | D31: Current approved MappingVersion change labels relative to prior approved state. | One current/historical change label per governed relationship version represented in output. | E31: Unresolved relationship outcome remains separate from change-state composition. | F31: Count governed relationships by the existing change labels; no speed/value claim inferred. | G31: visual → change class → Changes & Revalidation → relationship → evidence | H31: 1622 | I31: AVAILABLE
A32: V4 | B32: Governed cost / forecast view | C32: What governed cost/forecast amount can be shown by WBS scope? | D32: No sufficient quantitative contract supplied. | None admitted. | E32: All amount claims withheld. | F32: No aggregation performed. | G32: See Sources & Provenance / Assurance for withholding reason. | H32: 0 | I32: WITHHELD

Sheet 13 REVISIONS & PERIODS
A1: REVISIONS & PERIODS
A2: Which reporting revision this workbook is built on, what superseded what, and why only part of the governed relationship state reopened.
A3: Executive | B3: Issues | C3: Integration | D3: Project | E3: Changes | F3: Crosswalk | G3: Evidence | H3: Sources
A5: State of record | B5: MV-1 approved by Maya Chen, Owner Project Controls · 2026-10-16 14:11 UTC
A6: Built on these revisions | B6: Owner WBS (Initial Rev 0); Contractor Programme (Initial Rev 0); Cost & Forecast Control Accounts (Initial Rev 0); Commercial Package Register (Initial Rev 0)
A8: Selective revalidation in this version
A9: Relationships (unique) by change since the previous approved version -- the same composition as 07 CHANGES & REVALIDATION. Carried forward work was not rebuilt.
A10: Relationships in this version | B10: 1622
A11: Carried forward without rework | B11: 0
A12: Came back and were decided again (changed) | B12: 0
A13: New in this version | B13: 1622
A14: Retired (no longer reported) | B14: 0
A16: Source revision history
A17: Every revision supplied up to this approval, oldest first per source. CURRENT = the revision this version was approved against; SUPERSEDED = replaced within the same reporting period; HISTORICAL = the last revision of an earlier period. Added / Removed / Changed compare each revision's records with the previous revision of the same source (source content, not a relationship decision).
A18: Source | B18: Reporting period | C18: Revision | D18: Revision in period | E18: State | F18: Superseded by | G18: Effective from (UTC) | H18: Effective to (UTC) | I18: Data date | J18: Records | K18: Added | L18: Removed | M18: Changed | N18: Unchanged | O18: Approval basis | P18: File (SHA-256, first 12)
A19: Owner WBS | B19: Initial | C19: Rev 0 | D19: 0 | E19: CURRENT | G19: 2026-10-16 14:10:28 | I19: 2026-06-30 | J19: 79 | O19: Approved basis | P19: 37a40d25ac86
A20: Contractor Programme | B20: Initial | C20: Rev 0 | D20: 0 | E20: CURRENT | G20: 2026-10-16 14:10:29 | I20: 2026-06-30 | J20: 1082 | O20: Approved basis | P20: 3fd2ce3d07c0
A21: Cost & Forecast Control Accounts | B21: Initial | C21: Rev 0 | D21: 0 | E21: CURRENT | G21: 2026-10-16 14:10:30 | I21: 2026-06-30 | J21: 480 | O21: Approved basis | P21: 729f36ae0e36
A22: Commercial Package Register | B22: Initial | C22: Rev 0 | D22: 0 | E22: CURRENT | G22: 2026-10-16 14:10:30 | I22: 2026-06-30 | J22: 60 | O22: Approved basis | P22: 69e50b85c924
A24: Approval history
A25: Each approved mapping version, the source revisions it was approved against, and how much of its relationship state was carried forward versus decided again.
A26: Stable mapping reference | B26: Status | C26: Approved by | D26: Approved at (UTC) | E26: Approved against | F26: Relationships | G26: Carried forward | H26: Changed, re-decided | I26: New | J26: Retired
A27: MV-1 | B27: State of record | C27: Maya Chen, Owner Project Controls | D27: 2026-10-16 14:11:18 | E27: Owner WBS (Initial Rev 0); Contractor Programme (Initial Rev 0); Cost & Forecast Control Accounts (Initial Rev 0); Commercial Package Register (Initial Rev 0) | F27: 1622 | G27: 0 | H27: 0 | I27: 1622 | J27: 0
A29: Came back for a decision in this version
A30: Only these relationships were reopened, new or retired; every other relationship was carried forward with its original basis and approver.
A31: Relationship | B31: Record | C31: Change | D31: Reason | E31: Decided by | F31: Evidence
A32: R1083-v1 | B32: CST-01-001 | C32: New | D32: Record first supplied in this revision | F32: 10 EVIDENCE & DECISIONS
A33: R1084-v1 | B33: CST-01-002 | C33: New | D33: Record first supplied in this revision | F33: 10 EVIDENCE & DECISIONS
A34: R1085-v1 | B34: CST-01-003 | C34: New | D34: Record first supplied in this revision | F34: 10 EVIDENCE & DECISIONS
A35: R1086-v1 | B35: CST-01-004 | C35: New | D35: Record first supplied in this revision | F35: 10 EVIDENCE & DECISIONS
A36: R1087-v1 | B36: CST-01-005 | C36: New | D36: Record first supplied in this revision | F36: 10 EVIDENCE & DECISIONS
A37: R1088-v1 | B37: CST-01-006 | C37: New | D37: Record first supplied in this revision | F37: 10 EVIDENCE & DECISIONS
A38: R1089-v1 | B38: CST-01-007 | C38: New | D38: Record first supplied in this revision | F38: 10 EVIDENCE & DECISIONS
A39: R1090-v1 | B39: CST-01-008 | C39: New | D39: Record first supplied in this revision | F39: 10 EVIDENCE & DECISIONS
A40: R1091-v1 | B40: CST-01-009 | C40: New | D40: Record first supplied in this revision | F40: 10 EVIDENCE & DECISIONS
A41: R1092-v1 | B41: CST-01-010 | C41: New | D41: Record first supplied in this revision | F41: 10 EVIDENCE & DECISIONS
A42: R1093-v1 | B42: CST-01-011 | C42: New | D42: Record first supplied in this revision | F42: 10 EVIDENCE & DECISIONS
A43: R1094-v1 | B43: CST-01-012 | C43: New | D43: Record first supplied in this revision | F43: 10 EVIDENCE & DECISIONS
... A194: R1245-v1 | B194: CST-03-003 | C194: New | D194: Record first supplied in this revision | F194: 10 EVIDENCE & DECISIONS
A195: R1246-v2 | B195: CST-03-004 | C195: New | D195: Record first supplied in this revision | E195: Maya Chen, Owner Project Controls | F195: 10 EVIDENCE & DECISIONS
A196: R1247-v1 | B196: CST-03-005 | C196: New | D196: Record first supplied in this revision | F196: 10 EVIDENCE & DECISIONS
A197: R1248-v1 | B197: CST-03-006 | C197: New | D197: Record first supplied in this revision | F197: 10 EVIDENCE & DECISIONS
A198: R1249-v1 | B198: CST-03-007 | C198: New | D198: Record first supplied in this revision | F198: 10 EVIDENCE & DECISIONS
A199: R1250-v1 | B199: CST-03-008 | C199: New | D199: Record first supplied in this revision | F199: 10 EVIDENCE & DECISIONS
A200: R1251-v1 | B200: CST-03-009 | C200: New | D200: Record first supplied in this revision | F200: 10 EVIDENCE & DECISIONS
A201: R1252-v1 | B201: CST-03-010 | C201: New | D201: Record first supplied in this revision | F201: 10 EVIDENCE & DECISIONS
A202: R1253-v1 | B202: CST-03-011 | C202: New | D202: Record first supplied in this revision | F202: 10 EVIDENCE & DECISIONS
A203: R1254-v1 | B203: CST-03-012 | C203: New | D203: Record first supplied in this revision | F203: 10 EVIDENCE & DECISIONS
A204: R1255-v1 | B204: CST-03-013 | C204: New | D204: Record first supplied in this revision | F204: 10 EVIDENCE & DECISIONS
A205: R1256-v1 | B205: CST-03-014 | C205: New | D205: Record first supplied in this revision | F205: 10 EVIDENCE & DECISIONS
A206: R1257-v1 | B206: CST-03-015 | C206: New | D206: Record first supplied in this revision | F206: 10 EVIDENCE & DECISIONS
A207: R1258-v1 | B207: CST-03-016 | C207: New | D207: Record first supplied in this revision | F207: 10 EVIDENCE & DECISIONS
... A351: R1402-v1 | B351: CST-04-080 | C351: New | D351: Record first supplied in this revision | F351: 10 EVIDENCE & DECISIONS
A352: R1403-v2 | B352: CST-05-001 | C352: New | D352: Record first supplied in this revision | E352: Maya Chen, Owner Project Controls | F352: 10 EVIDENCE & DECISIONS
A353: R1404-v2 | B353: CST-05-002 | C353: New | D353: Record first supplied in this revision | E353: Maya Chen, Owner Project Controls | F353: 10 EVIDENCE & DECISIONS
A354: R1405-v2 | B354: CST-05-003 | C354: New | D354: Record first supplied in this revision | E354: Maya Chen, Owner Project Controls | F354: 10 EVIDENCE & DECISIONS
A355: R1406-v2 | B355: CST-05-004 | C355: New | D355: Record first supplied in this revision | E355: Maya Chen, Owner Project Controls | F355: 10 EVIDENCE & DECISIONS
A356: R1407-v2 | B356: CST-05-005 | C356: New | D356: Record first supplied in this revision | E356: Maya Chen, Owner Project Controls | F356: 10 EVIDENCE & DECISIONS
A357: R1408-v2 | B357: CST-05-006 | C357: New | D357: Record first supplied in this revision | E357: Maya Chen, Owner Project Controls | F357: 10 EVIDENCE & DECISIONS
A358: R1409-v2 | B358: CST-05-007 | C358: New | D358: Record first supplied in this revision | E358: Maya Chen, Owner Project Controls | F358: 10 EVIDENCE & DECISIONS
A359: R1410-v2 | B359: CST-05-008 | C359: New | D359: Record first supplied in this revision | E359: Maya Chen, Owner Project Controls | F359: 10 EVIDENCE & DECISIONS
A360: R1411-v2 | B360: CST-05-009 | C360: New | D360: Record first supplied in this revision | E360: Maya Chen, Owner Project Controls | F360: 10 EVIDENCE & DECISIONS
A361: R1412-v2 | B361: CST-05-010 | C361: New | D361: Record first supplied in this revision | E361: Maya Chen, Owner Project Controls | F361: 10 EVIDENCE & DECISIONS
A362: R1413-v2 | B362: CST-05-011 | C362: New | D362: Record first supplied in this revision | E362: Maya Chen, Owner Project Controls | F362: 10 EVIDENCE & DECISIONS
A363: R1414-v2 | B363: CST-05-012 | C363: New | D363: Record first supplied in this revision | E363: Maya Chen, Owner Project Controls | F363: 10 EVIDENCE & DECISIONS
... A431: R1482-v2 | B431: CST-05-080 | C431: New | D431: Record first supplied in this revision | E431: Maya Chen, Owner Project Controls | F431: 10 EVIDENCE & DECISIONS
A432: R1483-v1 | B432: CST-06-001 | C432: New | D432: Record first supplied in this revision | F432: 10 EVIDENCE & DECISIONS
A433: R1484-v1 | B433: CST-06-002 | C433: New | D433: Record first supplied in this revision | F433: 10 EVIDENCE & DECISIONS
A434: R1485-v1 | B434: CST-06-003 | C434: New | D434: Record first supplied in this revision | F434: 10 EVIDENCE & DECISIONS
A435: R1486-v1 | B435: CST-06-004 | C435: New | D435: Record first supplied in this revision | F435: 10 EVIDENCE & DECISIONS
A436: R1487-v1 | B436: CST-06-005 | C436: New | D436: Record first supplied in this revision | F436: 10 EVIDENCE & DECISIONS
A437: R1488-v1 | B437: CST-06-006 | C437: New | D437: Record first supplied in this revision | F437: 10 EVIDENCE & DECISIONS
A438: R1489-v1 | B438: CST-06-007 | C438: New | D438: Record first supplied in this revision | F438: 10 EVIDENCE & DECISIONS
A439: R1490-v1 | B439: CST-06-008 | C439: New | D439: Record first supplied in this revision | F439: 10 EVIDENCE & DECISIONS
A440: R1491-v1 | B440: CST-06-009 | C440: New | D440: Record first supplied in this revision | F440: 10 EVIDENCE & DECISIONS
A441: R1492-v1 | B441: CST-06-010 | C441: New | D441: Record first supplied in this revision | F441: 10 EVIDENCE & DECISIONS
A442: R1493-v1 | B442: CST-06-011 | C442: New | D442: Record first supplied in this revision | F442: 10 EVIDENCE & DECISIONS
A443: R1494-v1 | B443: CST-06-012 | C443: New | D443: Record first supplied in this revision | F443: 10 EVIDENCE & DECISIONS
... A511: R1562-v1 | B511: CST-06-080 | C511: New | D511: Record first supplied in this revision | F511: 10 EVIDENCE & DECISIONS
A512: R1563-v2 | B512: PKG-001 | C512: New | D512: Record first supplied in this revision | E512: Maya Chen, Owner Project Controls | F512: 10 EVIDENCE & DECISIONS
A513: R1564-v1 | B513: PKG-002 | C513: New | D513: Record first supplied in this revision | F513: 10 EVIDENCE & DECISIONS
A514: R1565-v1 | B514: PKG-003 | C514: New | D514: Record first supplied in this revision | F514: 10 EVIDENCE & DECISIONS
A515: R1566-v1 | B515: PKG-004 | C515: New | D515: Record first supplied in this revision | F515: 10 EVIDENCE & DECISIONS
A516: R1567-v1 | B516: PKG-005 | C516: New | D516: Record first supplied in this revision | F516: 10 EVIDENCE & DECISIONS
A517: R1568-v1 | B517: PKG-006 | C517: New | D517: Record first supplied in this revision | F517: 10 EVIDENCE & DECISIONS
A518: R1569-v1 | B518: PKG-007 | C518: New | D518: Record first supplied in this revision | F518: 10 EVIDENCE & DECISIONS
A519: R1570-v1 | B519: PKG-008 | C519: New | D519: Record first supplied in this revision | F519: 10 EVIDENCE & DECISIONS
A520: R1571-v1 | B520: PKG-009 | C520: New | D520: Record first supplied in this revision | F520: 10 EVIDENCE & DECISIONS
A521: R1572-v1 | B521: PKG-010 | C521: New | D521: Record first supplied in this revision | F521: 10 EVIDENCE & DECISIONS
A522: R1573-v1 | B522: PKG-011 | C522: New | D522: Record first supplied in this revision | F522: 10 EVIDENCE & DECISIONS
A523: R1574-v1 | B523: PKG-012 | C523: New | D523: Record first supplied in this revision | F523: 10 EVIDENCE & DECISIONS
A524: R1575-v1 | B524: PKG-013 | C524: New | D524: Record first supplied in this revision | F524: 10 EVIDENCE & DECISIONS
... A753: R182-v1 | B753: SCH-02-002 | C753: New | D753: Record first supplied in this revision | F753: 10 EVIDENCE & DECISIONS
A754: R183-v2 | B754: SCH-02-003 | C754: New | D754: Record first supplied in this revision | E754: Maya Chen, Owner Project Controls | F754: 10 EVIDENCE & DECISIONS
A755: R184-v1 | B755: SCH-02-004 | C755: New | D755: Record first supplied in this revision | F755: 10 EVIDENCE & DECISIONS
A756: R185-v1 | B756: SCH-02-005 | C756: New | D756: Record first supplied in this revision | F756: 10 EVIDENCE & DECISIONS
A757: R186-v1 | B757: SCH-02-006 | C757: New | D757: Record first supplied in this revision | F757: 10 EVIDENCE & DECISIONS
A758: R187-v1 | B758: SCH-02-007 | C758: New | D758: Record first supplied in this revision | F758: 10 EVIDENCE & DECISIONS
A759: R188-v1 | B759: SCH-02-008 | C759: New | D759: Record first supplied in this revision | F759: 10 EVIDENCE & DECISIONS
A760: R189-v1 | B760: SCH-02-009 | C760: New | D760: Record first supplied in this revision | F760: 10 EVIDENCE & DECISIONS
...

Sheet 14 WBS HIERARCHY
A1: WBS HIERARCHY
A2: The approved WBS as a scope hierarchy. Use the outline buttons (1, 2, 3 ...) at the left to collapse or expand levels; counts recalculate from MASTER DATA.
A3: Executive | B3: Issues | C3: Integration | D3: Project | E3: Changes | F3: Crosswalk | G3: Evidence | H3: Sources
A4: Advanced scope tree / relationship ROW counts → primary relationship coverage/status view
A5: Counts are relationship ROWS in MASTER DATA: one row per record-to-WBS target. A relationship split across several WBS targets has one row per target; NO_WBS / NEW_SCOPE / UNSURE rows carry the outcome in the WBS Code column; retired rows (Relationship State RETIRED) are included, as in MASTER DATA -- filter Relationship State to exclude them. Branch = this element and every element beneath it.
A6: Level | B6: WBS | C6: Hierarchy | D6: L1 | E6: L2 | F6: L3 | G6: L4 | H6: Direct relationship rows | I6: Branch relationship rows | J6: Crosswalk
A7: 1 | B7: 1 | C7: 1 HarbourLink Urban Transit Expansion | D7: 1 HarbourLink Urban Transit Expansion | H7: =COUNTIF('MASTER DATA'!$A$2:$A$1624,"=1") | I7: =SUM(H7:H85) | J7: 08 CROSSWALK
A8: 2 | B8: 1.1 | C8: ├─ 1.1 Guideway and Civil | E8: 1.1 Guideway and Civil | H8: =COUNTIF('MASTER DATA'!$A$2:$A$1624,"=1.1") | I8: =SUM(H8:H20) | J8: 08 CROSSWALK
A9: 3 | B9: 1.1.1 | C9: │ ├─ 1.1.1 Guideway and Civil - Guideway Structures | F9: 1.1.1 Guideway and Civil - Guideway Structures | H9: =COUNTIF('MASTER DATA'!$A$2:$A$1624,"=1.1.1") | I9: =SUM(H9:H11) | J9: 08 CROSSWALK
A10: 4 | B10: 1.1.1.1 | C10: │ │ ├─ 1.1.1.1 Guideway Structures - East Segment | G10: 1.1.1.1 Guideway Structures - East Segment | H10: =COUNTIF('MASTER DATA'!$A$2:$A$1624,"=1.1.1.1") | I10: =SUM(H10:H10) | J10: No relationships
A11: 4 | B11: 1.1.1.2 | C11: │ │ └─ 1.1.1.2 Guideway Structures - West Segment | G11: 1.1.1.2 Guideway Structures - West Segment | H11: =COUNTIF('MASTER DATA'!$A$2:$A$1624,"=1.1.1.2") | I11: =SUM(H11:H11) | J11: No relationships
A12: 3 | B12: 1.1.2 | C12: │ ├─ 1.1.2 Guideway and Civil - Utility & Roadworks | F12: 1.1.2 Guideway and Civil - Utility & Roadworks | H12: =COUNTIF('MASTER DATA'!$A$2:$A$1624,"=1.1.2") | I12: =SUM(H12:H14) | J12: 08 CROSSWALK
A13: 4 | B13: 1.1.2.1 | C13: │ │ ├─ 1.1.2.1 Utility & Roadworks - East Segment | G13: 1.1.2.1 Utility & Roadworks - East Segment | H13: =COUNTIF('MASTER DATA'!$A$2:$A$1624,"=1.1.2.1") | I13: =SUM(H13:H13) | J13: No relationships
A14: 4 | B14: 1.1.2.2 | C14: │ │ └─ 1.1.2.2 Utility & Roadworks - West Segment | G14: 1.1.2.2 Utility & Roadworks - West Segment | H14: =COUNTIF('MASTER DATA'!$A$2:$A$1624,"=1.1.2.2") | I14: =SUM(H14:H14) | J14: No relationships
A15: 3 | B15: 1.1.3 | C15: │ ├─ 1.1.3 Guideway and Civil - Track Support Works | F15: 1.1.3 Guideway and Civil - Track Support Works | H15: =COUNTIF('MASTER DATA'!$A$2:$A$1624,"=1.1.3") | I15: =SUM(H15:H17) | J15: No relationships
A16: 4 | B16: 1.1.3.1 | C16: │ │ ├─ 1.1.3.1 Track Support Works - East Segment | G16: 1.1.3.1 Track Support Works - East Segment | H16: =COUNTIF('MASTER DATA'!$A$2:$A$1624,"=1.1.3.1") | I16: =SUM(H16:H16) | J16: No relationships
A17: 4 | B17: 1.1.3.2 | C17: │ │ └─ 1.1.3.2 Track Support Works - West Segment | G17: 1.1.3.2 Track Support Works - West Segment | H17: =COUNTIF('MASTER DATA'!$A$2:$A$1624,"=1.1.3.2") | I17: =SUM(H17:H17) | J17: No relationships
A18: 3 | B18: 1.1.4 | C18: │ └─ 1.1.4 Guideway and Civil - Civil Interfaces | F18: 1.1.4 Guideway and Civil - Civil Interfaces | H18: =COUNTIF('MASTER DATA'!$A$2:$A$1624,"=1.1.4") | I18: =SUM(H18:H20) | J18: No relationships
A19: 4 | B19: 1.1.4.1 | C19: │ ├─ 1.1.4.1 Civil Interfaces - East Segment | G19: 1.1.4.1 Civil Interfaces - East Segment | H19: =COUNTIF('MASTER DATA'!$A$2:$A$1624,"=1.1.4.1") | I19: =SUM(H19:H19) | J19: No relationships
A20: 4 | B20: 1.1.4.2 | C20: │ └─ 1.1.4.2 Civil Interfaces - West Segment | G20: 1.1.4.2 Civil Interfaces - West Segment | H20: =COUNTIF('MASTER DATA'!$A$2:$A$1624,"=1.1.4.2") | I20: =SUM(H20:H20) | J20: No relationships
A21: 2 | B21: 1.2 | C21: ├─ 1.2 Stations | E21: 1.2 Stations | H21: =COUNTIF('MASTER DATA'!$A$2:$A$1624,"=1.2") | I21: =SUM(H21:H33) | J21: 08 CROSSWALK
A22: 3 | B22: 1.2.1 | C22: │ ├─ 1.2.1 Stations - Station Structures | F22: 1.2.1 Stations - Station Structures | H22: =COUNTIF('MASTER DATA'!$A$2:$A$1624,"=1.2.1") | I22: =SUM(H22:H24) | J22: 08 CROSSWALK
A23: 4 | B23: 1.2.1.1 | C23: │ │ ├─ 1.2.1.1 Station Structures - Concourse & Entries | G23: 1.2.1.1 Station Structures - Concourse & Entries | H23: =COUNTIF('MASTER DATA'!$A$2:$A$1624,"=1.2.1.1") | I23: =SUM(H23:H23) | J23: No relationships
A24: 4 | B24: 1.2.1.2 | C24: │ │ └─ 1.2.1.2 Station Structures - Platforms & Back-of-House | G24: 1.2.1.2 Station Structures - Platforms & Back-of-House | H24: =COUNTIF('MASTER DATA'!$A$2:$A$1624,"=1.2.1.2") | I24: =SUM(H24:H24) | J24: No relationships
A25: 3 | B25: 1.2.2 | C25: │ ├─ 1.2.2 Stations - Architectural Fit-Out | F25: 1.2.2 Stations - Architectural Fit-Out | H25: =COUNTIF('MASTER DATA'!$A$2:$A$1624,"=1.2.2") | I25: =SUM(H25:H27) | J25: 08 CROSSWALK
A26: 4 | B26: 1.2.2.1 | C26: │ │ ├─ 1.2.2.1 Architectural Fit-Out - Concourse & Entries | G26: 1.2.2.1 Architectural Fit-Out - Concourse & Entries | H26: =COUNTIF('MASTER DATA'!$A$2:$A$1624,"=1.2.2.1") | I26: =SUM(H26:H26) | J26: No relationships
A27: 4 | B27: 1.2.2.2 | C27: │ │ └─ 1.2.2.2 Architectural Fit-Out - Platforms & Back-of-House | G27: 1.2.2.2 Architectural Fit-Out - Platforms & Back-of-House | H27: =COUNTIF('MASTER DATA'!$A$2:$A$1624,"=1.2.2.2") | I27: =SUM(H27:H27) | J27: No relationships
A28: 3 | B28: 1.2.3 | C28: │ ├─ 1.2.3 Stations - Station Building Services | F28: 1.2.3 Stations - Station Building Services | H28: =COUNTIF('MASTER DATA'!$A$2:$A$1624,"=1.2.3") | I28: =SUM(H28:H30) | J28: No relationships
A29: 4 | B29: 1.2.3.1 | C29: │ │ ├─ 1.2.3.1 Station Building Services - Concourse & Entries | G29: 1.2.3.1 Station Building Services - Concourse & Entries | H29: =COUNTIF('MASTER DATA'!$A$2:$A$1624,"=1.2.3.1") | I29: =SUM(H29:H29) | J29: No relationships
A30: 4 | B30: 1.2.3.2 | C30: │ │ └─ 1.2.3.2 Station Building Services - Platforms & Back-of-House | G30: 1.2.3.2 Station Building Services - Platforms & Back-of-House | H30: =COUNTIF('MASTER DATA'!$A$2:$A$1624,"=1.2.3.2") | I30: =SUM(H30:H30) | J30: No relationships
A31: 3 | B31: 1.2.4 | C31: │ └─ 1.2.4 Stations - Public Realm | F31: 1.2.4 Stations - Public Realm | H31: =COUNTIF('MASTER DATA'!$A$2:$A$1624,"=1.2.4") | I31: =SUM(H31:H33) | J31: No relationships
A32: 4 | B32: 1.2.4.1 | C32: │ ├─ 1.2.4.1 Public Realm - Concourse & Entries | G32: 1.2.4.1 Public Realm - Concourse & Entries | H32: =COUNTIF('MASTER DATA'!$A$2:$A$1624,"=1.2.4.1") | I32: =SUM(H32:H32) | J32: No relationships
A33: 4 | B33: 1.2.4.2 | C33: │ └─ 1.2.4.2 Public Realm - Platforms & Back-of-House | G33: 1.2.4.2 Public Realm - Platforms & Back-of-House | H33: =COUNTIF('MASTER DATA'!$A$2:$A$1624,"=1.2.4.2") | I33: =SUM(H33:H33) | J33: No relationships
A34: 2 | B34: 1.3 | C34: ├─ 1.3 Systems | E34: 1.3 Systems | H34: =COUNTIF('MASTER DATA'!$A$2:$A$1624,"=1.3") | I34: =SUM(H34:H46) | J34: 08 CROSSWALK
A35: 3 | B35: 1.3.1 | C35: │ ├─ 1.3.1 Systems - Traction Power | F35: 1.3.1 Systems - Traction Power | H35: =COUNTIF('MASTER DATA'!$A$2:$A$1624,"=1.3.1") | I35: =SUM(H35:H37) | J35: 08 CROSSWALK
A36: 4 | B36: 1.3.1.1 | C36: │ │ ├─ 1.3.1.1 Traction Power - Wayside | G36: 1.3.1.1 Traction Power - Wayside | H36: =COUNTIF('MASTER DATA'!$A$2:$A$1624,"=1.3.1.1") | I36: =SUM(H36:H36) | J36: No relationships
A37: 4 | B37: 1.3.1.2 | C37: │ │ └─ 1.3.1.2 Traction Power - Control Centre & Stations | G37: 1.3.1.2 Traction Power - Control Centre & Stations | H37: =COUNTIF('MASTER DATA'!$A$2:$A$1624,"=1.3.1.2") | I37: =SUM(H37:H37) | J37: No relationships
A38: 3 | B38: 1.3.2 | C38: │ ├─ 1.3.2 Systems - Signalling & Train Control | F38: 1.3.2 Systems - Signalling & Train Control | H38: =COUNTIF('MASTER DATA'!$A$2:$A$1624,"=1.3.2") | I38: =SUM(H38:H40) | J38: 08 CROSSWALK
A39: 4 | B39: 1.3.2.1 | C39: │ │ ├─ 1.3.2.1 Signalling & Train Control - Wayside | G39: 1.3.2.1 Signalling & Train Control - Wayside | H39: =COUNTIF('MASTER DATA'!$A$2:$A$1624,"=1.3.2.1") | I39: =SUM(H39:H39) | J39: No relationships
A40: 4 | B40: 1.3.2.2 | C40: │ │ └─ 1.3.2.2 Signalling & Train Control - Control Centre & Stations | G40: 1.3.2.2 Signalling & Train Control - Control Centre & Stations | H40: =COUNTIF('MASTER DATA'!$A$2:$A$1624,"=1.3.2.2") | I40: =SUM(H40:H40) | J40: No relationships
A41: 3 | B41: 1.3.3 | C41: │ ├─ 1.3.3 Systems - Communications | F41: 1.3.3 Systems - Communications | H41: =COUNTIF('MASTER DATA'!$A$2:$A$1624,"=1.3.3") | I41: =SUM(H41:H43) | J41: No relationships
A42: 4 | B42: 1.3.3.1 | C42: │ │ ├─ 1.3.3.1 Communications - Wayside | G42: 1.3.3.1 Communications - Wayside | H42: =COUNTIF('MASTER DATA'!$A$2:$A$1624,"=1.3.3.1") | I42: =SUM(H42:H42) | J42: No relationships
A43: 4 | B43: 1.3.3.2 | C43: │ │ └─ 1.3.3.2 Communications - Control Centre & Stations | G43: 1.3.3.2 Communications - Control Centre & Stations | H43: =COUNTIF('MASTER DATA'!$A$2:$A$1624,"=1.3.3.2") | I43: =SUM(H43:H43) | J43: No relationships
A44: 3 | B44: 1.3.4 | C44: │ └─ 1.3.4 Systems - Systems Integration | F44: 1.3.4 Systems - Systems Integration | H44: =COUNTIF('MASTER DATA'!$A$2:$A$1624,"=1.3.4") | I44: =SUM(H44:H46) | J44: No relationships
A45: 4 | B45: 1.3.4.1 | C45: │ ├─ 1.3.4.1 Systems Integration - Wayside | G45: 1.3.4.1 Systems Integration - Wayside | H45: =COUNTIF('MASTER DATA'!$A$2:$A$1624,"=1.3.4.1") | I45: =SUM(H45:H45) | J45: No relationships
A46: 4 | B46: 1.3.4.2 | C46: │ └─ 1.3.4.2 Systems Integration - Control Centre & Stations | G46: 1.3.4.2 Systems Integration - Control Centre & Stations | H46: =COUNTIF('MASTER DATA'!$A$2:$A$1624,"=1.3.4.2") | I46: =SUM(H46:H46) | J46: No relationships
A47: 2 | B47: 1.4 | C47: ├─ 1.4 Vehicles and Depot | E47: 1.4 Vehicles and Depot | H47: =COUNTIF('MASTER DATA'!$A$2:$A$1624,"=1.4") | I47: =SUM(H47:H59) | J47: 08 CROSSWALK
A48: 3 | B48: 1.4.1 | C48: │ ├─ 1.4.1 Vehicles and Depot - Fleet Supply | F48: 1.4.1 Vehicles and Depot - Fleet Supply | H48: =COUNTIF('MASTER DATA'!$A$2:$A$1624,"=1.4.1") | I48: =SUM(H48:H50) | J48: 08 CROSSWALK
A49: 4 | B49: 1.4.1.1 | C49: │ │ ├─ 1.4.1.1 Fleet Supply - Maintenance Facility | G49: 1.4.1.1 Fleet Supply - Maintenance Facility | H49: =COUNTIF('MASTER DATA'!$A$2:$A$1624,"=1.4.1.1") | I49: =SUM(H49:H49) | J49: No relationships
A50: 4 | B50: 1.4.1.2 | C50: │ │ └─ 1.4.1.2 Fleet Supply - Storage & Commissioning Yard | G50: 1.4.1.2 Fleet Supply - Storage & Commissioning Yard | H50: =COUNTIF('MASTER DATA'!$A$2:$A$1624,"=1.4.1.2") | I50: =SUM(H50:H50) | J50: No relationships
A51: 3 | B51: 1.4.2 | C51: │ ├─ 1.4.2 Vehicles and Depot - Depot Buildings | F51: 1.4.2 Vehicles and Depot - Depot Buildings | H51: =COUNTIF('MASTER DATA'!$A$2:$A$1624,"=1.4.2") | I51: =SUM(H51:H53) | J51: 08 CROSSWALK
A52: 4 | B52: 1.4.2.1 | C52: │ │ ├─ 1.4.2.1 Depot Buildings - Maintenance Facility | G52: 1.4.2.1 Depot Buildings - Maintenance Facility | H52: =COUNTIF('MASTER DATA'!$A$2:$A$1624,"=1.4.2.1") | I52: =SUM(H52:H52) | J52: No relationships
A53: 4 | B53: 1.4.2.2 | C53: │ │ └─ 1.4.2.2 Depot Buildings - Storage & Commissioning Yard | G53: 1.4.2.2 Depot Buildings - Storage & Commissioning Yard | H53: =COUNTIF('MASTER DATA'!$A$2:$A$1624,"=1.4.2.2") | I53: =SUM(H53:H53) | J53: No relationships
A54: 3 | B54: 1.4.3 | C54: │ ├─ 1.4.3 Vehicles and Depot - Workshop Equipment | F54: 1.4.3 Vehicles and Depot - Workshop Equipment | H54: =COUNTIF('MASTER DATA'!$A$2:$A$1624,"=1.4.3") | I54: =SUM(H54:H56) | J54: No relationships
A55: 4 | B55: 1.4.3.1 | C55: │ │ ├─ 1.4.3.1 Workshop Equipment - Maintenance Facility | G55: 1.4.3.1 Workshop Equipment - Maintenance Facility | H55: =COUNTIF('MASTER DATA'!$A$2:$A$1624,"=1.4.3.1") | I55: =SUM(H55:H55) | J55: No relationships
A56: 4 | B56: 1.4.3.2 | C56: │ │ └─ 1.4.3.2 Workshop Equipment - Storage & Commissioning Yard | G56: 1.4.3.2 Workshop Equipment - Storage & Commissioning Yard | H56: =COUNTIF('MASTER DATA'!$A$2:$A$1624,"=1.4.3.2") | I56: =SUM(H56:H56) | J56: No relationships
A57: 3 | B57: 1.4.4 | C57: │ └─ 1.4.4 Vehicles and Depot - Vehicle Integration | F57: 1.4.4 Vehicles and Depot - Vehicle Integration | H57: =COUNTIF('MASTER DATA'!$A$2:$A$1624,"=1.4.4") | I57: =SUM(H57:H59) | J57: No relationships
A58: 4 | B58: 1.4.4.1 | C58: │ ├─ 1.4.4.1 Vehicle Integration - Maintenance Facility | G58: 1.4.4.1 Vehicle Integration - Maintenance Facility | H58: =COUNTIF('MASTER DATA'!$A$2:$A$1624,"=1.4.4.1") | I58: =SUM(H58:H58) | J58: No relationships
A59: 4 | B59: 1.4.4.2 | C59: │ └─ 1.4.4.2 Vehicle Integration - Storage & Commissioning Yard | G59: 1.4.4.2 Vehicle Integration - Storage & Commissioning Yard | H59: =COUNTIF('MASTER DATA'!$A$2:$A$1624,"=1.4.4.2") | I59: =SUM(H59:H59) | J59: No relationships
A60: 2 | B60: 1.5 | C60: ├─ 1.5 Testing and Commissioning | E60: 1.5 Testing and Commissioning | H60: =COUNTIF('MASTER DATA'!$A$2:$A$1624,"=1.5") | I60: =SUM(H60:H72) | J60: 08 CROSSWALK
A61: 3 | B61: 1.5.1 | C61: │ ├─ 1.5.1 Testing and Commissioning - Test Readiness | F61: 1.5.1 Testing and Commissioning - Test Readiness | H61: =COUNTIF('MASTER DATA'!$A$2:$A$1624,"=1.5.1") | I61: =SUM(H61:H63) | J61: 08 CROSSWALK
A62: 4 | B62: 1.5.1.1 | C62: │ │ ├─ 1.5.1.1 Test Readiness - Mainline | G62: 1.5.1.1 Test Readiness - Mainline | H62: =COUNTIF('MASTER DATA'!$A$2:$A$1624,"=1.5.1.1") | I62: =SUM(H62:H62) | J62: No relationships
A63: 4 | B63: 1.5.1.2 | C63: │ │ └─ 1.5.1.2 Test Readiness - Depot & Stations | G63: 1.5.1.2 Test Readiness - Depot & Stations | H63: =COUNTIF('MASTER DATA'!$A$2:$A$1624,"=1.5.1.2") | I63: =SUM(H63:H63) | J63: No relationships
A64: 3 | B64: 1.5.2 | C64: │ ├─ 1.5.2 Testing and Commissioning - Dynamic Testing | F64: 1.5.2 Testing and Commissioning - Dynamic Testing | H64: =COUNTIF('MASTER DATA'!$A$2:$A$1624,"=1.5.2") | I64: =SUM(H64:H66) | J64: 08 CROSSWALK
A65: 4 | B65: 1.5.2.1 | C65: │ │ ├─ 1.5.2.1 Dynamic Testing - Mainline | G65: 1.5.2.1 Dynamic Testing - Mainline | H65: =COUNTIF('MASTER DATA'!$A$2:$A$1624,"=1.5.2.1") | I65: =SUM(H65:H65) | J65: No relationships
A66: 4 | B66: 1.5.2.2 | C66: │ │ └─ 1.5.2.2 Dynamic Testing - Depot & Stations | G66: 1.5.2.2 Dynamic Testing - Depot & Stations | H66: =COUNTIF('MASTER DATA'!$A$2:$A$1624,"=1.5.2.2") | I66: =SUM(H66:H66) | J66: No relationships
A67: 3 | B67: 1.5.3 | C67: │ ├─ 1.5.3 Testing and Commissioning - Safety Certification | F67: 1.5.3 Testing and Commissioning - Safety Certification | H67: =COUNTIF('MASTER DATA'!$A$2:$A$1624,"=1.5.3") | I67: =SUM(H67:H69) | J67: No relationships
A68: 4 | B68: 1.5.3.1 | C68: │ │ ├─ 1.5.3.1 Safety Certification - Mainline | G68: 1.5.3.1 Safety Certification - Mainline | H68: =COUNTIF('MASTER DATA'!$A$2:$A$1624,"=1.5.3.1") | I68: =SUM(H68:H68) | J68: No relationships
A69: 4 | B69: 1.5.3.2 | C69: │ │ └─ 1.5.3.2 Safety Certification - Depot & Stations | G69: 1.5.3.2 Safety Certification - Depot & Stations | H69: =COUNTIF('MASTER DATA'!$A$2:$A$1624,"=1.5.3.2") | I69: =SUM(H69:H69) | J69: No relationships
A70: 3 | B70: 1.5.4 | C70: │ └─ 1.5.4 Testing and Commissioning - Service Readiness | F70: 1.5.4 Testing and Commissioning - Service Readiness | H70: =COUNTIF('MASTER DATA'!$A$2:$A$1624,"=1.5.4") | I70: =SUM(H70:H72) | J70: No relationships
A71: 4 | B71: 1.5.4.1 | C71: │ ├─ 1.5.4.1 Service Readiness - Mainline | G71: 1.5.4.1 Service Readiness - Mainline | H71: =COUNTIF('MASTER DATA'!$A$2:$A$1624,"=1.5.4.1") | I71: =SUM(H71:H71) | J71: No relationships
A72: 4 | B72: 1.5.4.2 | C72: │ └─ 1.5.4.2 Service Readiness - Depot & Stations | G72: 1.5.4.2 Service Readiness - Depot & Stations | H72: =COUNTIF('MASTER DATA'!$A$2:$A$1624,"=1.5.4.2") | I72: =SUM(H72:H72) | J72: No relationships
A73: 2 | B73: 1.6 | C73: └─ 1.6 Program Management | E73: 1.6 Program Management | H73: =COUNTIF('MASTER DATA'!$A$2:$A$1624,"=1.6") | I73: =SUM(H73:H85) | J73: 08 CROSSWALK
A74: 3 | B74: 1.6.1 | C74: ├─ 1.6.1 Program Management - Program Controls | F74: 1.6.1 Program Management - Program Controls | H74: =COUNTIF('MASTER DATA'!$A$2:$A$1624,"=1.6.1") | I74: =SUM(H74:H76) | J74: 08 CROSSWALK
A75: 4 | B75: 1.6.1.1 | C75: │ ├─ 1.6.1.1 Program Controls - Owner Team | G75: 1.6.1.1 Program Controls - Owner Team | H75: =COUNTIF('MASTER DATA'!$A$2:$A$1624,"=1.6.1.1") | I75: =SUM(H75:H75) | J75: No relationships
A76: 4 | B76: 1.6.1.2 | C76: │ └─ 1.6.1.2 Program Controls - Delivery Partners | G76: 1.6.1.2 Program Controls - Delivery Partners | H76: =COUNTIF('MASTER DATA'!$A$2:$A$1624,"=1.6.1.2") | I76: =SUM(H76:H76) | J76: No relationships
A77: 3 | B77: 1.6.2 | C77: ├─ 1.6.2 Program Management - Commercial & Procurement | F77: 1.6.2 Program Management - Commercial & Procurement | H77: =COUNTIF('MASTER DATA'!$A$2:$A$1624,"=1.6.2") | I77: =SUM(H77:H79) | J77: 08 CROSSWALK
A78: 4 | B78: 1.6.2.1 | C78: │ ├─ 1.6.2.1 Commercial & Procurement - Owner Team | G78: 1.6.2.1 Commercial & Procurement - Owner Team | H78: =COUNTIF('MASTER DATA'!$A$2:$A$1624,"=1.6.2.1") | I78: =SUM(H78:H78) | J78: No relationships
A79: 4 | B79: 1.6.2.2 | C79: │ └─ 1.6.2.2 Commercial & Procurement - Delivery Partners | G79: 1.6.2.2 Commercial & Procurement - Delivery Partners | H79: =COUNTIF('MASTER DATA'!$A$2:$A$1624,"=1.6.2.2") | I79: =SUM(H79:H79) | J79: No relationships
A80: 3 | B80: 1.6.3 | C80: ├─ 1.6.3 Program Management - Stakeholder & Permits | F80: 1.6.3 Program Management - Stakeholder & Permits | H80: =COUNTIF('MASTER DATA'!$A$2:$A$1624,"=1.6.3") | I80: =SUM(H80:H82) | J80: No relationships
A81: 4 | B81: 1.6.3.1 | C81: │ ├─ 1.6.3.1 Stakeholder & Permits - Owner Team | G81: 1.6.3.1 Stakeholder & Permits - Owner Team | H81: =COUNTIF('MASTER DATA'!$A$2:$A$1624,"=1.6.3.1") | I81: =SUM(H81:H81) | J81: No relationships
A82: 4 | B82: 1.6.3.2 | C82: │ └─ 1.6.3.2 Stakeholder & Permits - Delivery Partners | G82: 1.6.3.2 Stakeholder & Permits - Delivery Partners | H82: =COUNTIF('MASTER DATA'!$A$2:$A$1624,"=1.6.3.2") | I82: =SUM(H82:H82) | J82: No relationships
A83: 3 | B83: 1.6.4 | C83: └─ 1.6.4 Program Management - Delivery Integration | F83: 1.6.4 Program Management - Delivery Integration | H83: =COUNTIF('MASTER DATA'!$A$2:$A$1624,"=1.6.4") | I83: =SUM(H83:H85) | J83: No relationships
A84: 4 | B84: 1.6.4.1 | C84: ├─ 1.6.4.1 Delivery Integration - Owner Team | G84: 1.6.4.1 Delivery Integration - Owner Team | H84: =COUNTIF('MASTER DATA'!$A$2:$A$1624,"=1.6.4.1") | I84: =SUM(H84:H84) | J84: No relationships
A85: 4 | B85: 1.6.4.2 | C85: └─ 1.6.4.2 Delivery Integration - Delivery Partners | G85: 1.6.4.2 Delivery Integration - Delivery Partners | H85: =COUNTIF('MASTER DATA'!$A$2:$A$1624,"=1.6.4.2") | I85: =SUM(H85:H85) | J85: No relationships
A87: Not attached to an element of this WBS (unresolved outcome or retired)
B88: NEW_SCOPE | H88: =COUNTIF('MASTER DATA'!$A$2:$A$1624,"=NEW_SCOPE")
B89: NO_WBS | H89: =COUNTIF('MASTER DATA'!$A$2:$A$1624,"=NO_WBS")
B90: UNSURE | H90: =COUNTIF('MASTER DATA'!$A$2:$A$1624,"=UNSURE")
A92: Total relationship rows (MASTER DATA) | H92: =COUNTA('MASTER DATA'!$O$2:$O$1624)
A93: Check: elements + not attached = total | H93: =IF(SUM(H7:H85)+SUM(H88:H90)=COUNTA('MASTER DATA'!$O$2:$O$1624),"reconciled","DOES NOT RECONCILE")

Sheet 15 ANALYSIS
A1: ANALYSIS
A2: Governed dimensions cross-tabulated from MASTER DATA. Native Excel formulas: they recalculate from the record-level rows and check themselves against the total.
A3: Executive | B3: Issues | C3: Integration | D3: Project | E3: Changes | F3: Crosswalk | G3: Evidence | H3: Sources
A5: Counts are relationship ROWS in MASTER DATA: one row per record-to-WBS target. A relationship split across several WBS targets has one row per target; NO_WBS / NEW_SCOPE / UNSURE rows carry the outcome in the WBS Code column; retired rows (Relationship State RETIRED) are included, as in MASTER DATA -- filter Relationship State to exclude them.
A7: Relationship state × basis of authority
A8: Who or what established each relationship row: professional decision, carried-forward decision, source assignment, approved project rule, or WBS↔LINK (not individually reviewed).
A9: Relationship State | B9: Professional decision | C9: Source assignment -- not individually reviewed | D9: Total | E9: Inspect
A10: APPROVED | B10: =COUNTIFS('MASTER DATA'!$G$2:$G$1624,"=APPROVED",'MASTER DATA'!$I$2:$I$1624,"=Professional decision") | C10: =COUNTIFS('MASTER DATA'!$G$2:$G$1624,"=APPROVED",'MASTER DATA'!$I$2:$I$1624,"=Source assignment -- not individually reviewed") | D10: =SUM(B10:C10) | E10: 08 CROSSWALK
A11: Total | B11: =SUM(B10:B10) | C11: =SUM(C10:C10) | D11: =SUM(D10:D10)
A12: Check: total equals MASTER DATA rows | B12: =IF(D11=COUNTA('MASTER DATA'!$O$2:$O$1624),"reconciled","DOES NOT RECONCILE")
A14: Reporting period · revision × change since the previous approved version
A15: Which source revision each relationship row rests on, and whether it was carried forward, revalidated, decided again, new or retired.
A16: Source Document · Reporting Period · Revision | B16: New | C16: Total | D16: Inspect
A17: Commercial Package Register · Initial · Rev 0 | B17: =COUNTIFS('MASTER DATA'!$C$2:$C$1624,"=Commercial Package Register",'MASTER DATA'!$M$2:$M$1624,"=Initial",'MASTER DATA'!$N$2:$N$1624,"=Rev 0",'MASTER DATA'!$H$2:$H$1624,"=New") | C17: =SUM(B17:B17) | D17: 08 CROSSWALK
A18: Contractor Programme · Initial · Rev 0 | B18: =COUNTIFS('MASTER DATA'!$C$2:$C$1624,"=Contractor Programme",'MASTER DATA'!$M$2:$M$1624,"=Initial",'MASTER DATA'!$N$2:$N$1624,"=Rev 0",'MASTER DATA'!$H$2:$H$1624,"=New") | C18: =SUM(B18:B18) | D18: 08 CROSSWALK
A19: Cost & Forecast Control Accounts · Initial · Rev 0 | B19: =COUNTIFS('MASTER DATA'!$C$2:$C$1624,"=Cost & Forecast Control Accounts",'MASTER DATA'!$M$2:$M$1624,"=Initial",'MASTER DATA'!$N$2:$N$1624,"=Rev 0",'MASTER DATA'!$H$2:$H$1624,"=New") | C19: =SUM(B19:B19) | D19: 08 CROSSWALK
A20: Total | B20: =SUM(B17:B19) | C20: =SUM(C17:C19)
A21: Check: total equals MASTER DATA rows | B21: =IF(C20=COUNTA('MASTER DATA'!$O$2:$O$1624),"reconciled","DOES NOT RECONCILE")
A23: Relationship type × relationship state
A24: Includes unresolved outcomes (NO_WBS, NEW_SCOPE, UNSURE) as their own types: uncertainty is counted, never hidden.
A25: Relationship Type | B25: APPROVED | C25: Total | D25: Inspect
A26: NEW_SCOPE | B26: =COUNTIFS('MASTER DATA'!$F$2:$F$1624,"=NEW_SCOPE",'MASTER DATA'!$G$2:$G$1624,"=APPROVED") | C26: =SUM(B26:B26) | D26: 08 CROSSWALK
A27: NO_WBS | B27: =COUNTIFS('MASTER DATA'!$F$2:$F$1624,"=NO_WBS",'MASTER DATA'!$G$2:$G$1624,"=APPROVED") | C27: =SUM(B27:B27) | D27: 08 CROSSWALK
A28: ONE_TO_MANY | B28: =COUNTIFS('MASTER DATA'!$F$2:$F$1624,"=ONE_TO_MANY",'MASTER DATA'!$G$2:$G$1624,"=APPROVED") | C28: =SUM(B28:B28) | D28: 08 CROSSWALK
A29: ONE_TO_ONE | B29: =COUNTIFS('MASTER DATA'!$F$2:$F$1624,"=ONE_TO_ONE",'MASTER DATA'!$G$2:$G$1624,"=APPROVED") | C29: =SUM(B29:B29) | D29: 08 CROSSWALK
A30: UNSURE | B30: =COUNTIFS('MASTER DATA'!$F$2:$F$1624,"=UNSURE",'MASTER DATA'!$G$2:$G$1624,"=APPROVED") | C30: =SUM(B30:B30) | D30: 08 CROSSWALK
A31: Total | B31: =SUM(B26:B30) | C31: =SUM(C26:C30)
A32: Check: total equals MASTER DATA rows | B32: =IF(C31=COUNTA('MASTER DATA'!$O$2:$O$1624),"reconciled","DOES NOT RECONCILE")
A34: Use the formula tables to analyse approved records. This workbook does not contain generated PivotTables or slicers. To create your own PivotTable, select the named range WBSLINK_GOVERNED_RECORDS.

Sheet MASTER DATA
A1: WBS Code | B1: WBS Name | C1: Source Document | D1: Source Record ID | E1: Description | F1: Relationship Type | G1: Relationship State | H1: Change vs Previous Version | I1: Basis | J1: Decided By | K1: Proposed By | L1: Allocation | M1: Reporting Period | N1: Revision | O1: Relationship ID | P1: Target Status | Q1: Evidence Note | R1: Recommended WBS (not approved) | S1: Ancestor Status | T1: Decision Scope | U1: Reopen Reason | V1: Source Assertion | W1: Contrary Source Evidence
A2: 1.1 | B2: Guideway and Civil | C2: Commercial Package Register | D2: PKG-001 | E2: Guideway Civil Works | F2: ONE_TO_MANY | G2: APPROVED | H2: New | I2: Professional decision | J2: Maya Chen, Owner Project Controls | K2: Professional | L2: Split -- basis to be confirmed | M2: Initial | N2: Rev 0 | O2: R1563-v2 | T2: Individual | V2: Package Code = PK-101; WBS Code = 1.1;1.2 | W2: Source states 'WBS Code' = '1.1;1.2' -- names no element of this WBS -- professional reason (Maya Chen, Owner Project Controls): Source package register explicitly states both Owner-WBS branches.
A3: 1.1 | B3: Guideway and Civil | C3: Commercial Package Register | D3: PKG-002 | E3: Utility Relocations | F3: ONE_TO_ONE | G3: APPROVED | H3: New | I3: Source assignment -- not individually reviewed | K3: Source assignment | M3: Initial | N3: Rev 0 | O3: R1564-v1 | V3: Package Code = PK-102; WBS Code = 1.1
A4: 1.1 | B4: Guideway and Civil | C4: Commercial Package Register | D4: PKG-003 | E4: Road & Drainage | F4: ONE_TO_ONE | G4: APPROVED | H4: New | I4: Source assignment -- not individually reviewed | K4: Source assignment | M4: Initial | N4: Rev 0 | O4: R1565-v1 | V4: Package Code = PK-103; WBS Code = 1.1
A5: 1.1 | B5: Guideway and Civil | C5: Commercial Package Register | D5: PKG-004 | E5: Track Support Works | F5: ONE_TO_ONE | G5: APPROVED | H5: New | I5: Source assignment -- not individually reviewed | K5: Source assignment | M5: Initial | N5: Rev 0 | O5: R1566-v1 | V5: Package Code = PK-104; WBS Code = 1.1
A6: 1.1 | B6: Guideway and Civil | C6: Commercial Package Register | D6: PKG-005 | E6: Guideway Civil Works - Lot 2 | F6: ONE_TO_ONE | G6: APPROVED | H6: New | I6: Source assignment -- not individually reviewed | K6: Source assignment | M6: Initial | N6: Rev 0 | O6: R1567-v1 | V6: Package Code = PK-105; WBS Code = 1.1
A7: 1.1 | B7: Guideway and Civil | C7: Commercial Package Register | D7: PKG-006 | E7: Utility Relocations - Lot 2 | F7: ONE_TO_ONE | G7: APPROVED | H7: New | I7: Source assignment -- not individually reviewed | K7: Source assignment | M7: Initial | N7: Rev 0 | O7: R1568-v1 | V7: Package Code = PK-106; WBS Code = 1.1
A8: 1.1 | B8: Guideway and Civil | C8: Commercial Package Register | D8: PKG-007 | E8: Road & Drainage - Lot 2 | F8: ONE_TO_ONE | G8: APPROVED | H8: New | I8: Source assignment -- not individually reviewed | K8: Source assignment | M8: Initial | N8: Rev 0 | O8: R1569-v1 | V8: Package Code = PK-107; WBS Code = 1.1
A9: 1.1 | B9: Guideway and Civil | C9: Commercial Package Register | D9: PKG-008 | E9: Track Support Works - Lot 2 | F9: ONE_TO_ONE | G9: APPROVED | H9: New | I9: Source assignment -- not individually reviewed | K9: Source assignment | M9: Initial | N9: Rev 0 | O9: R1570-v1 | V9: Package Code = PK-108; WBS Code = 1.1
A10: 1.1 | B10: Guideway and Civil | C10: Commercial Package Register | D10: PKG-009 | E10: Guideway Civil Works - Lot 3 | F10: ONE_TO_ONE | G10: APPROVED | H10: New | I10: Source assignment -- not individually reviewed | K10: Source assignment | M10: Initial | N10: Rev 0 | O10: R1571-v1 | V10: Package Code = PK-109; WBS Code = 1.1
A11: 1.1 | B11: Guideway and Civil | C11: Commercial Package Register | D11: PKG-010 | E11: Utility Relocations - Lot 3 | F11: ONE_TO_ONE | G11: APPROVED | H11: New | I11: Source assignment -- not individually reviewed | K11: Source assignment | M11: Initial | N11: Rev 0 | O11: R1572-v1 | V11: Package Code = PK-110; WBS Code = 1.1
A12: 1.1.1 | B12: Guideway and Civil - Guideway Structures | C12: Contractor Programme | D12: SCH-01-001 | E12: West approach: track-slab survey - installation | F12: ONE_TO_ONE | G12: APPROVED | H12: New | I12: Source assignment -- not individually reviewed | K12: Source assignment | M12: Initial | N12: Rev 0 | O12: R1-v1 | V12: WBS Code = 1.1.1
A13: 1.1.1 | B13: Guideway and Civil - Guideway Structures | C13: Contractor Programme | D13: SCH-01-002 | E13: Depot lead: temporary traffic staging - inspection | F13: ONE_TO_ONE | G13: APPROVED | H13: New | I13: Source assignment -- not individually reviewed | K13: Source assignment | M13: Initial | N13: Rev 0 | O13: R2-v1 | V13: WBS Code = 1.1.1
A14: 1.1.1 | B14: Guideway and Civil - Guideway Structures | C14: Contractor Programme | D14: SCH-01-004 | E14: River crossing: road restoration - release | F14: ONE_TO_ONE | G14: APPROVED | H14: New | I14: Source assignment -- not individually reviewed | K14: Source assignment | M14: Initial | N14: Rev 0 | O14: R4-v1 | V14: WBS Code = 1.1.1
... A271: 1.1.2 | B271: Guideway and Civil - Utility & Roadworks | C271: Cost & Forecast Control Accounts | D271: CST-01-080 | E271: Guideway and Civil - temporary works - supply and install | F271: ONE_TO_ONE | G271: APPROVED | H271: New | I271: Source assignment -- not individually reviewed | K271: Source assignment | M271: Initial | N271: Rev 0 | O271: R1162-v1 | V271: Cost Account = CA-1080; WBS Code = 1.1.2
A272: 1.2 | B272: Stations | C272: Commercial Package Register | D272: PKG-001 | E272: Guideway Civil Works | F272: ONE_TO_MANY | G272: APPROVED | H272: New | I272: Professional decision | J272: Maya Chen, Owner Project Controls | K272: Professional | L272: Split -- basis to be confirmed | M272: Initial | N272: Rev 0 | O272: R1563-v2 | T272: Individual | V272: Package Code = PK-101; WBS Code = 1.1;1.2 | W272: Source states 'WBS Code' = '1.1;1.2' -- names no element of this WBS -- professional reason (Maya Chen, Owner Project Controls): Source package register explicitly states both Owner-WBS branches.
A273: 1.2 | B273: Stations | C273: Commercial Package Register | D273: PKG-011 | E273: Station Structural Works | F273: ONE_TO_ONE | G273: APPROVED | H273: New | I273: Source assignment -- not individually reviewed | K273: Source assignment | M273: Initial | N273: Rev 0 | O273: R1573-v1 | V273: Package Code = PK-201; WBS Code = 1.2
A274: 1.2 | B274: Stations | C274: Commercial Package Register | D274: PKG-012 | E274: Station Fit-Out | F274: ONE_TO_ONE | G274: APPROVED | H274: New | I274: Source assignment -- not individually reviewed | K274: Source assignment | M274: Initial | N274: Rev 0 | O274: R1574-v1 | V274: Package Code = PK-202; WBS Code = 1.2
A275: 1.2 | B275: Stations | C275: Commercial Package Register | D275: PKG-013 | E275: Building Services | F275: ONE_TO_ONE | G275: APPROVED | H275: New | I275: Source assignment -- not individually reviewed | K275: Source assignment | M275: Initial | N275: Rev 0 | O275: R1575-v1 | V275: Package Code = PK-203; WBS Code = 1.2
A276: 1.2 | B276: Stations | C276: Commercial Package Register | D276: PKG-014 | E276: Public Realm | F276: ONE_TO_ONE | G276: APPROVED | H276: New | I276: Source assignment -- not individually reviewed | K276: Source assignment | M276: Initial | N276: Rev 0 | O276: R1576-v1 | V276: Package Code = PK-204; WBS Code = 1.2
A277: 1.2 | B277: Stations | C277: Commercial Package Register | D277: PKG-015 | E277: Station Structural Works - Lot 2 | F277: ONE_TO_ONE | G277: APPROVED | H277: New | I277: Source assignment -- not individually reviewed | K277: Source assignment | M277: Initial | N277: Rev 0 | O277: R1577-v1 | V277: Package Code = PK-205; WBS Code = 1.2
A278: 1.2 | B278: Stations | C278: Commercial Package Register | D278: PKG-016 | E278: Station Fit-Out - Lot 2 | F278: ONE_TO_ONE | G278: APPROVED | H278: New | I278: Source assignment -- not individually reviewed | K278: Source assignment | M278: Initial | N278: Rev 0 | O278: R1578-v1 | V278: Package Code = PK-206; WBS Code = 1.2
A279: 1.2 | B279: Stations | C279: Commercial Package Register | D279: PKG-017 | E279: Building Services - Lot 2 | F279: ONE_TO_ONE | G279: APPROVED | H279: New | I279: Source assignment -- not individually reviewed | K279: Source assignment | M279: Initial | N279: Rev 0 | O279: R1579-v1 | V279: Package Code = PK-207; WBS Code = 1.2
A280: 1.2 | B280: Stations | C280: Commercial Package Register | D280: PKG-018 | E280: Public Realm - Lot 2 | F280: ONE_TO_ONE | G280: APPROVED | H280: New | I280: Source assignment -- not individually reviewed | K280: Source assignment | M280: Initial | N280: Rev 0 | O280: R1580-v1 | V280: Package Code = PK-208; WBS Code = 1.2
A281: 1.2 | B281: Stations | C281: Commercial Package Register | D281: PKG-019 | E281: Station Structural Works - Lot 3 | F281: ONE_TO_ONE | G281: APPROVED | H281: New | I281: Source assignment -- not individually reviewed | K281: Source assignment | M281: Initial | N281: Rev 0 | O281: R1581-v1 | V281: Package Code = PK-209; WBS Code = 1.2
A282: 1.2 | B282: Stations | C282: Commercial Package Register | D282: PKG-020 | E282: Station Fit-Out - Lot 3 | F282: ONE_TO_ONE | G282: APPROVED | H282: New | I282: Source assignment -- not individually reviewed | K282: Source assignment | M282: Initial | N282: Rev 0 | O282: R1582-v1 | V282: Package Code = PK-210; WBS Code = 1.2
A283: 1.2.1 | B283: Stations - Station Structures | C283: Contractor Programme | D283: SCH-02-001 | E283: Harbour Station: vertical-transport installation - inspection | F283: ONE_TO_ONE | G283: APPROVED | H283: New | I283: Source assignment -- not individually reviewed | K283: Source assignment | M283: Initial | N283: Rev 0 | O283: R181-v1 | V283: WBS Code = 1.2.1
A284: 1.2.1 | B284: Stations - Station Structures | C284: Contractor Programme | D284: SCH-02-002 | E284: Market Station: platform edge installation - turnover | F284: ONE_TO_ONE | G284: APPROVED | H284: New | I284: Source assignment -- not individually reviewed | K284: Source assignment | M284: Initial | N284: Rev 0 | O284: R182-v1 | V284: WBS Code = 1.2.1
... A1359: 1.6.2 | B1359: Program Management - Commercial & Procurement | C1359: Cost & Forecast Control Accounts | D1359: CST-06-080 | E1359: Program Management - stakeholder services - supply and install | F1359: ONE_TO_ONE | G1359: APPROVED | H1359: New | I1359: Source assignment -- not individually reviewed | K1359: Source assignment | M1359: Initial | N1359: Rev 0 | O1359: R1562-v1 | V1359: Cost Account = CA-6080; WBS Code = 1.6.2
A1360: NEW_SCOPE | C1360: Contractor Programme | D1360: SCH-90-901 | E1360: Temporary offsite logistics compound | F1360: NEW_SCOPE | G1360: APPROVED | H1360: New | I1360: Professional decision | J1360: Maya Chen, Owner Project Controls | K1360: Professional | M1360: Initial | N1360: Rev 0 | O1360: R1081-v2 | T1360: Individual | V1360: WBS Code = 2.1 | W1360: Source states 'WBS Code' = '2.1' -- names no element of this WBS -- professional reason (Maya Chen, Owner Project Controls): Source states a project-delivery code outside the currently approved Owner WBS.
A1361: NO_WBS | C1361: Contractor Programme | D1361: SCH-90-902 | E1361: Corporate training unrelated to project delivery scope | F1361: NO_WBS | G1361: APPROVED | H1361: New | I1361: Professional decision | J1361: Maya Chen, Owner Project Controls | K1361: Professional | M1361: Initial | N1361: Rev 0 | O1361: R1082-v2 | T1361: Individual
A1362: UNSURE | C1362: Contractor Programme | D1362: SCH-02-003 | E1362: Interface works near stations boundary | F1362: UNSURE | G1362: APPROVED | H1362: New | I1362: Professional decision | J1362: Maya Chen, Owner Project Controls | K1362: Professional | M1362: Initial | N1362: Rev 0 | O1362: R183-v2 | T1362: Group decision (182 records sharing one decision state)
A1363: UNSURE | C1363: Contractor Programme | D1363: SCH-04-003 | E1363: Interface works near vehicles and depot boundary | F1363: UNSURE | G1363: APPROVED | H1363: New | I1363: Professional decision | J1363: Maya Chen, Owner Project Controls | K1363: Professional | M1363: Initial | N1363: Rev 0 | O1363: R543-v2 | T1363: Group decision (182 records sharing one decision state)
A1364: UNSURE | C1364: Contractor Programme | D1364: SCH-06-001 | E1364: Systems package: commercial change review - installation | F1364: UNSURE | G1364: APPROVED | H1364: New | I1364: Professional decision | J1364: Maya Chen, Owner Project Controls | K1364: Professional | M1364: Initial | N1364: Rev 0 | O1364: R901-v2 | T1364: Group decision (182 records sharing one decision state)
A1365: UNSURE | C1365: Contractor Programme | D1365: SCH-06-002 | E1365: Fleet package: design-package integration review - inspection | F1365: UNSURE | G1365: APPROVED | H1365: New | I1365: Professional decision | J1365: Maya Chen, Owner Project Controls | K1365: Professional | M1365: Initial | N1365: Rev 0 | O1365: R902-v2 | T1365: Group decision (182 records sharing one decision state)
A1366: UNSURE | C1366: Contractor Programme | D1366: SCH-06-003 | E1366: Interface works near program management boundary | F1366: UNSURE | G1366: APPROVED | H1366: New | I1366: Professional decision | J1366: Maya Chen, Owner Project Controls | K1366: Professional | M1366: Initial | N1366: Rev 0 | O1366: R903-v2 | T1366: Group decision (182 records sharing one decision state)
A1367: UNSURE | C1367: Contractor Programme | D1367: SCH-06-004 | E1367: Civil package: permit coordination - release | F1367: UNSURE | G1367: APPROVED | H1367: New | I1367: Professional decision | J1367: Maya Chen, Owner Project Controls | K1367: Professional | M1367: Initial | N1367: Rev 0 | O1367: R904-v2 | T1367: Group decision (182 records sharing one decision state)
A1368: UNSURE | C1368: Contractor Programme | D1368: SCH-06-005 | E1368: Stations package: delivery risk workshop - field start | F1368: UNSURE | G1368: APPROVED | H1368: New | I1368: Professional decision | J1368: Maya Chen, Owner Project Controls | K1368: Professional | M1368: Initial | N1368: Rev 0 | O1368: R905-v2 | T1368: Group decision (182 records sharing one decision state)
A1369: UNSURE | C1369: Contractor Programme | D1369: SCH-06-006 | E1369: Systems package: monthly controls cut-off - installation | F1369: UNSURE | G1369: APPROVED | H1369: New | I1369: Professional decision | J1369: Maya Chen, Owner Project Controls | K1369: Professional | M1369: Initial | N1369: Rev 0 | O1369: R906-v2 | T1369: Group decision (182 records sharing one decision state)
A1370: UNSURE | C1370: Contractor Programme | D1370: SCH-06-007 | E1370: Fleet package: stakeholder interface meeting - inspection | F1370: UNSURE | G1370: APPROVED | H1370: New | I1370: Professional decision | J1370: Maya Chen, Owner Project Controls | K1370: Professional | M1370: Initial | N1370: Rev 0 | O1370: R907-v2 | T1370: Group decision (182 records sharing one decision state)
A1371: UNSURE | C1371: Contractor Programme | D1371: SCH-06-008 | E1371: Program office: baseline change control - turnover | F1371: UNSURE | G1371: APPROVED | H1371: New | I1371: Professional decision | J1371: Maya Chen, Owner Project Controls | K1371: Professional | M1371: Initial | N1371: Rev 0 | O1371: R908-v2 | T1371: Group decision (182 records sharing one decision state)
A1372: UNSURE | C1372: Contractor Programme | D1372: SCH-06-009 | E1372: Civil package: commercial change review - release | F1372: UNSURE | G1372: APPROVED | H1372: New | I1372: Professional decision | J1372: Maya Chen, Owner Project Controls | K1372: Professional | M1372: Initial | N1372: Rev 0 | O1372: R909-v2 | T1372: Group decision (182 records sharing one decision state)
... A1543: UNSURE | C1543: Contractor Programme | D1543: SCH-06-180 | E1543: Stations package: permit coordination - field start | F1543: UNSURE | G1543: APPROVED | H1543: New | I1543: Professional decision | J1543: Maya Chen, Owner Project Controls | K1543: Professional | M1543: Initial | N1543: Rev 0 | O1543: R1080-v2 | T1543: Group decision (182 records sharing one decision state)
A1544: UNSURE | C1544: Cost & Forecast Control Accounts | D1544: CST-03-004 | E1544: Systems - systems integration - professional services | F1544: UNSURE | G1544: APPROVED | H1544: New | I1544: Professional decision | J1544: Maya Chen, Owner Project Controls | K1544: Professional | M1544: Initial | N1544: Rev 0 | O1544: R1246-v2 | T1544: Group decision (81 records sharing one decision state) | V1544: Cost Account = CA-3004
A1545: UNSURE | C1545: Cost & Forecast Control Accounts | D1545: CST-05-001 | E1545: Testing & readiness - trial running - control account | F1545: UNSURE | G1545: APPROVED | H1545: New | I1545: Professional decision | J1545: Maya Chen, Owner Project Controls | K1545: Professional | M1545: Initial | N1545: Rev 0 | O1545: R1403-v2 | T1545: Group decision (81 records sharing one decision state) | V1545: Cost Account = CA-5001
A1546: UNSURE | C1546: Cost & Forecast Control Accounts | D1546: CST-05-002 | E1546: Testing & readiness - safety certification - control account | F1546: UNSURE | G1546: APPROVED | H1546: New | I1546: Professional decision | J1546: Maya Chen, Owner Project Controls | K1546: Professional | M1546: Initial | N1546: Rev 0 | O1546: R1404-v2 | T1546: Group decision (81 records sharing one decision state) | V1546: Cost Account = CA-5002
A1547: UNSURE | C1547: Cost & Forecast Control Accounts | D1547: CST-05-003 | E1547: Testing & readiness - defect closeout - control account | F1547: UNSURE | G1547: APPROVED | H1547: New | I1547: Professional decision | J1547: Maya Chen, Owner Project Controls | K1547: Professional | M1547: Initial | N1547: Rev 0 | O1547: R1405-v2 | T1547: Group decision (81 records sharing one decision state) | V1547: Cost Account = CA-5003
A1548: UNSURE | C1548: Cost & Forecast Control Accounts | D1548: CST-05-004 | E1548: Testing & readiness - test management - control account | F1548: UNSURE | G1548: APPROVED | H1548: New | I1548: Professional decision | J1548: Maya Chen, Owner Project Controls | K1548: Professional | M1548: Initial | N1548: Rev 0 | O1548: R1406-v2 | T1548: Group decision (81 records sharing one decision state) | V1548: Cost Account = CA-5004
A1549: UNSURE | C1549: Cost & Forecast Control Accounts | D1549: CST-05-005 | E1549: Testing & readiness - trial running - control account | F1549: UNSURE | G1549: APPROVED | H1549: New | I1549: Professional decision | J1549: Maya Chen, Owner Project Controls | K1549: Professional | M1549: Initial | N1549: Rev 0 | O1549: R1407-v2 | T1549: Group decision (81 records sharing one decision state) | V1549: Cost Account = CA-5005
A1550: UNSURE | C1550: Cost & Forecast Control Accounts | D1550: CST-05-006 | E1550: Testing & readiness - safety certification - control account | F1550: UNSURE | G1550: APPROVED | H1550: New | I1550: Professional decision | J1550: Maya Chen, Owner Project Controls | K1550: Professional | M1550: Initial | N1550: Rev 0 | O1550: R1408-v2 | T1550: Group decision (81 records sharing one decision state) | V1550: Cost Account = CA-5006
A1551: UNSURE | C1551: Cost & Forecast Control Accounts | D1551: CST-05-007 | E1551: Testing & readiness - defect closeout - control account | F1551: UNSURE | G1551: APPROVED | H1551: New | I1551: Professional decision | J1551: Maya Chen, Owner Project Controls | K1551: Professional | M1551: Initial | N1551: Rev 0 | O1551: R1409-v2 | T1551: Group decision (81 records sharing one decision state) | V1551: Cost Account = CA-5007
A1552: UNSURE | C1552: Cost & Forecast Control Accounts | D1552: CST-05-008 | E1552: Testing & readiness - test management - control account | F1552: UNSURE | G1552: APPROVED | H1552: New | I1552: Professional decision | J1552: Maya Chen, Owner Project Controls | K1552: Professional | M1552: Initial | N1552: Rev 0 | O1552: R1410-v2 | T1552: Group decision (81 records sharing one decision state) | V1552: Cost Account = CA-5008
A1553: UNSURE | C1553: Cost & Forecast Control Accounts | D1553: CST-05-009 | E1553: Testing & readiness - trial running - control account | F1553: UNSURE | G1553: APPROVED | H1553: New | I1553: Professional decision | J1553: Maya Chen, Owner Project Controls | K1553: Professional | M1553: Initial | N1553: Rev 0 | O1553: R1411-v2 | T1553: Group decision (81 records sharing one decision state) | V1553: Cost Account = CA-5009
A1554: UNSURE | C1554: Cost & Forecast Control Accounts | D1554: CST-05-010 | E1554: Testing & readiness - safety certification - control account | F1554: UNSURE | G1554: APPROVED | H1554: New | I1554: Professional decision | J1554: Maya Chen, Owner Project Controls | K1554: Professional | M1554: Initial | N1554: Rev 0 | O1554: R1412-v2 | T1554: Group decision (81 records sharing one decision state) | V1554: Cost Account = CA-5010
A1555: UNSURE | C1555: Cost & Forecast Control Accounts | D1555: CST-05-011 | E1555: Testing & readiness - defect closeout - control account | F1555: UNSURE | G1555: APPROVED | H1555: New | I1555: Professional decision | J1555: Maya Chen, Owner Project Controls | K1555: Professional | M1555: Initial | N1555: Rev 0 | O1555: R1413-v2 | T1555: Group decision (81 records sharing one decision state) | V1555: Cost Account = CA-5011
... A1624: UNSURE | C1624: Cost & Forecast Control Accounts | D1624: CST-05-080 | E1624: Testing & readiness - test management - control account | F1624: UNSURE | G1624: APPROVED | H1624: New | I1624: Professional decision | J1624: Maya Chen, Owner Project Controls | K1624: Professional | M1624: Initial | N1624: Rev 0 | O1624: R1482-v2 | T1624: Group decision (81 records sharing one decision state) | V1624: Cost Account = CA-5080

Sheet OWNER WBS
A1: Code | B1: Name | C1: Parent Code | D1: Represented Dimension | E1: Scope Nature | F1: Roll-up | G1: Provenance | H1: Current Rows Mapped
A2: 1 | B2: HarbourLink Urban Transit Expansion | E2: Deliverable | G2: System Proposed | H2: =COUNTIFS('MASTER DATA'!$A$2:$A$1624,A2,'MASTER DATA'!$G$2:$G$1624,"<>RETIRED")
A3: 1.1 | B3: Guideway and Civil | C3: 1 | E3: Deliverable | G3: System Proposed | H3: =COUNTIFS('MASTER DATA'!$A$2:$A$1624,A3,'MASTER DATA'!$G$2:$G$1624,"<>RETIRED")
A4: 1.1.1 | B4: Guideway and Civil - Guideway Structures | C4: 1.1 | E4: Deliverable | G4: System Proposed | H4: =COUNTIFS('MASTER DATA'!$A$2:$A$1624,A4,'MASTER DATA'!$G$2:$G$1624,"<>RETIRED")
A5: 1.1.1.1 | B5: Guideway Structures - East Segment | C5: 1.1.1 | E5: Deliverable | G5: System Proposed | H5: =COUNTIFS('MASTER DATA'!$A$2:$A$1624,A5,'MASTER DATA'!$G$2:$G$1624,"<>RETIRED")
A6: 1.1.1.2 | B6: Guideway Structures - West Segment | C6: 1.1.1 | E6: Deliverable | G6: System Proposed | H6: =COUNTIFS('MASTER DATA'!$A$2:$A$1624,A6,'MASTER DATA'!$G$2:$G$1624,"<>RETIRED")
A7: 1.1.2 | B7: Guideway and Civil - Utility & Roadworks | C7: 1.1 | E7: Deliverable | G7: System Proposed | H7: =COUNTIFS('MASTER DATA'!$A$2:$A$1624,A7,'MASTER DATA'!$G$2:$G$1624,"<>RETIRED")
A8: 1.1.2.1 | B8: Utility & Roadworks - East Segment | C8: 1.1.2 | E8: Deliverable | G8: System Proposed | H8: =COUNTIFS('MASTER DATA'!$A$2:$A$1624,A8,'MASTER DATA'!$G$2:$G$1624,"<>RETIRED")
A9: 1.1.2.2 | B9: Utility & Roadworks - West Segment | C9: 1.1.2 | E9: Deliverable | G9: System Proposed | H9: =COUNTIFS('MASTER DATA'!$A$2:$A$1624,A9,'MASTER DATA'!$G$2:$G$1624,"<>RETIRED")
A10: 1.1.3 | B10: Guideway and Civil - Track Support Works | C10: 1.1 | E10: Deliverable | G10: System Proposed | H10: =COUNTIFS('MASTER DATA'!$A$2:$A$1624,A10,'MASTER DATA'!$G$2:$G$1624,"<>RETIRED")
A11: 1.1.3.1 | B11: Track Support Works - East Segment | C11: 1.1.3 | E11: Deliverable | G11: System Proposed | H11: =COUNTIFS('MASTER DATA'!$A$2:$A$1624,A11,'MASTER DATA'!$G$2:$G$1624,"<>RETIRED")
A12: 1.1.3.2 | B12: Track Support Works - West Segment | C12: 1.1.3 | E12: Deliverable | G12: System Proposed | H12: =COUNTIFS('MASTER DATA'!$A$2:$A$1624,A12,'MASTER DATA'!$G$2:$G$1624,"<>RETIRED")
A13: 1.1.4 | B13: Guideway and Civil - Civil Interfaces | C13: 1.1 | E13: Deliverable | G13: System Proposed | H13: =COUNTIFS('MASTER DATA'!$A$2:$A$1624,A13,'MASTER DATA'!$G$2:$G$1624,"<>RETIRED")
A14: 1.1.4.1 | B14: Civil Interfaces - East Segment | C14: 1.1.4 | E14: Deliverable | G14: System Proposed | H14: =COUNTIFS('MASTER DATA'!$A$2:$A$1624,A14,'MASTER DATA'!$G$2:$G$1624,"<>RETIRED")
... A80: 1.6.4.2 | B80: Delivery Integration - Delivery Partners | C80: 1.6.4 | E80: Deliverable | G80: System Proposed | H80: =COUNTIFS('MASTER DATA'!$A$2:$A$1624,A80,'MASTER DATA'!$G$2:$G$1624,"<>RETIRED")

Sheet RELATIONSHIP EXPLORER
A1: WBS Code | B1: WBS Element | C1: Level | D1: Schedule | E1: Cost | F1: Package / Contract | G1: Other | H1: Governed | I1: Needing Attention | J1: Changed
A2: Supporting static scope projection. No formulas are supplied on this sheet; 09 WBS EXPLORER is the primary scope route. | B2: HarbourLink Urban Transit Expansion | C2: 0 | D2: 898 | E2: 399 | F2: 60 | G2: 0 | H2: 1357 | I2: 0 | J2: 1357
A3: 1 | B3: HarbourLink Urban Transit Expansion | C3: 1 | D3: 898 | E3: 399 | F3: 60 | G3: 0 | H3: 1357 | I3: 0 | J3: 1357
A4: 1.1 | B4: Guideway and Civil | C4: 2 | D4: 180 | E4: 80 | F4: 10 | G4: 0 | H4: 270 | I4: 0 | J4: 270
A5: 1.1.1 | B5: Guideway and Civil - Guideway Structures | C5: 3 | D5: 120 | E5: 40 | F5: 0 | G5: 0 | H5: 160 | I5: 0 | J5: 160
A6: 1.1.1.1 | B6: Guideway Structures - East Segment | C6: 4 | D6: 0 | E6: 0 | F6: 0 | G6: 0 | H6: 0 | I6: 0 | J6: 0
A7: 1.1.1.2 | B7: Guideway Structures - West Segment | C7: 4 | D7: 0 | E7: 0 | F7: 0 | G7: 0 | H7: 0 | I7: 0 | J7: 0
A8: 1.1.2 | B8: Guideway and Civil - Utility & Roadworks | C8: 3 | D8: 60 | E8: 40 | F8: 0 | G8: 0 | H8: 100 | I8: 0 | J8: 100
A9: 1.1.2.1 | B9: Utility & Roadworks - East Segment | C9: 4 | D9: 0 | E9: 0 | F9: 0 | G9: 0 | H9: 0 | I9: 0 | J9: 0
A10: 1.1.2.2 | B10: Utility & Roadworks - West Segment | C10: 4 | D10: 0 | E10: 0 | F10: 0 | G10: 0 | H10: 0 | I10: 0 | J10: 0
A11: 1.1.3 | B11: Guideway and Civil - Track Support Works | C11: 3 | D11: 0 | E11: 0 | F11: 0 | G11: 0 | H11: 0 | I11: 0 | J11: 0
A12: 1.1.3.1 | B12: Track Support Works - East Segment | C12: 4 | D12: 0 | E12: 0 | F12: 0 | G12: 0 | H12: 0 | I12: 0 | J12: 0
A13: 1.1.3.2 | B13: Track Support Works - West Segment | C13: 4 | D13: 0 | E13: 0 | F13: 0 | G13: 0 | H13: 0 | I13: 0 | J13: 0
... A81: 1.6.4.2 | B81: Delivery Integration - Delivery Partners | C81: 4 | D81: 0 | E81: 0 | F81: 0 | G81: 0 | H81: 0 | I81: 0 | J81: 0

Sheet UNRESOLVED
A1: SUPPORTING UNRESOLVED AND OUTSIDE-WBS RECORDS
A2: Current distinct outcomes requiring follow-up: 265. Retired rows may also be retained below; filter lifecycle status before counting current records.
A4: Source Document | B4: Source Record ID | C4: Description | D4: Relationship Type | E4: Decided By | F4: Basis | G4: Reporting lifecycle
A5: Contractor Programme | B5: SCH-90-901 | C5: Temporary offsite logistics compound | D5: NEW_SCOPE | E5: Maya Chen, Owner Project Controls | F5: Professional decision | G5: Current
A6: Contractor Programme | B6: SCH-90-902 | C6: Corporate training unrelated to project delivery scope | D6: NO_WBS | E6: Maya Chen, Owner Project Controls | F6: Professional decision | G6: Current
A7: Contractor Programme | B7: SCH-02-003 | C7: Interface works near stations boundary | D7: UNSURE | E7: Maya Chen, Owner Project Controls | F7: Professional decision | G7: Current
A8: Contractor Programme | B8: SCH-04-003 | C8: Interface works near vehicles and depot boundary | D8: UNSURE | E8: Maya Chen, Owner Project Controls | F8: Professional decision | G8: Current
A9: Contractor Programme | B9: SCH-06-001 | C9: Systems package: commercial change review - installation | D9: UNSURE | E9: Maya Chen, Owner Project Controls | F9: Professional decision | G9: Current
A10: Contractor Programme | B10: SCH-06-002 | C10: Fleet package: design-package integration review - inspection | D10: UNSURE | E10: Maya Chen, Owner Project Controls | F10: Professional decision | G10: Current
A11: Contractor Programme | B11: SCH-06-003 | C11: Interface works near program management boundary | D11: UNSURE | E11: Maya Chen, Owner Project Controls | F11: Professional decision | G11: Current
A12: Contractor Programme | B12: SCH-06-004 | C12: Civil package: permit coordination - release | D12: UNSURE | E12: Maya Chen, Owner Project Controls | F12: Professional decision | G12: Current
A13: Contractor Programme | B13: SCH-06-005 | C13: Stations package: delivery risk workshop - field start | D13: UNSURE | E13: Maya Chen, Owner Project Controls | F13: Professional decision | G13: Current
A14: Contractor Programme | B14: SCH-06-006 | C14: Systems package: monthly controls cut-off - installation | D14: UNSURE | E14: Maya Chen, Owner Project Controls | F14: Professional decision | G14: Current
A15: Contractor Programme | B15: SCH-06-007 | C15: Fleet package: stakeholder interface meeting - inspection | D15: UNSURE | E15: Maya Chen, Owner Project Controls | F15: Professional decision | G15: Current
... A269: Cost & Forecast Control Accounts | B269: CST-05-080 | C269: Testing & readiness - test management - control account | D269: UNSURE | E269: Maya Chen, Owner Project Controls | F269: Professional decision | G269: Current

Sheet HISTORY
A1: Mapping versions
A2: Approved sequence / stable reference | B2: Status | C2: Purpose | D2: Approved By | E2: Approved (UTC)
A3: Approved version 1 · stable mapping reference MV-1 · APPROVED | B3: SUPERSEDED | C3: REPORTING | D3: Maya Chen, Owner Project Controls | E3: 2026-10-16 14:11
A4: Approved version 2 · stable mapping reference MV-2 · APPROVED | B4: APPROVED | C4: REPORTING | D4: Maya Chen, Owner Project Controls | E4: 2026-10-16 14:14
A6: WBS versions
A7: WBS Version | B7: Status | C7: Approved By | D7: Effective From (UTC) | E7: Effective To (UTC)
A8: 1 | B8: ACTIVE | C8: Maya Chen, Owner Project Controls | D8: 2026-10-16 14:10

Sheet SUMMARY
A1: WBS↔LINK by ZP Synergy Group | R1: Advanced original field values
A2: Supporting reconciliation calculations. Read the approved management position only on 03 EXECUTIVE VIEW.
A3: Reconcile the approved workbook records and formula totals. These calculations support, rather than replace, the executive position. | R3: P5 | S3: Established: every materially populated supplied region has an established TABLE or CONTEXT interpretation, and every table used has a governed role. Output reconciliation shows that the Crosswalk, XLSX, PDF and JSON consume one governed state. It does not show that the upstream source representation is true: that is the source representation integrity gate.
A5: Project | B5: HarbourLink Urban Transit Expansion | O5: B15 original source interpretation | P5: Established: every materially populated supplied region has an established Source table or CONTEXT interpretation, and every table used has a governed role. Output reconciliation shows that the Crosswalk, XLSX, PDF and JSON consume one governed state. It does not show that the upstream source representation is true: that is the source representation integrity gate.
A6: Approval state | B6: APPROVED -- Maya Chen, Owner Project Controls, 2026-10-16 14:11 UTC
A7: Data date | B7: 2026-06-30 (Contractor Programme Rev 0); 2026-06-30 (Cost & Forecast Control Accounts Rev 0); 2026-06-30 (Commercial Package Register Rev 0)
A8: Generated (UTC) | B8: 2026-10-17 18:35
A9: Approved output identity | B9: Approved version 1 · stable mapping reference MV-1 · APPROVED
A10: Approved by | B10: Maya Chen, Owner Project Controls
A11: Approved (UTC) | B11: 2026-10-16 14:11
A12: Against WBS version | B12: 1, approved by Maya Chen, Owner Project Controls
A13: Source documents | B13: Contractor Programme (Rev 0); Cost & Forecast Control Accounts (Rev 0); Commercial Package Register (Rev 0)
A14: WBS generated from | B14: Owner WBS
A15: Source representation | B15: Established source interpretation and roles. Output consistency does not establish that a source assertion is correct; inspect the original evidence and professional decision separately.
A16: Workbook template edition | B16: Premium Workbook Rev 2
A18: Counts (live formulas over MASTER DATA)
A19: By change vs previous version
A20: Carried forward | B20: =COUNTIF('MASTER DATA'!$H$2:$H$1624,"Carried forward")
A21: Re-keyed, revalidated | B21: =COUNTIF('MASTER DATA'!$H$2:$H$1624,"Re-keyed, revalidated")
A22: Changed, re-decided | B22: =COUNTIF('MASTER DATA'!$H$2:$H$1624,"Changed, re-decided")
A23: New | B23: =COUNTIF('MASTER DATA'!$H$2:$H$1624,"New")
A24: Retired | B24: =COUNTIF('MASTER DATA'!$H$2:$H$1624,"Retired")
A25: By basis
A26: Professional decision | B26: =COUNTIF('MASTER DATA'!$I$2:$I$1624,"Professional decision")
A27: Earlier professional decision, carried forward | B27: =COUNTIF('MASTER DATA'!$I$2:$I$1624,"Earlier professional decision, carried forward")
A28: Source assignment -- not individually reviewed | B28: =COUNTIF('MASTER DATA'!$I$2:$I$1624,"Source assignment -- not individually reviewed")
A29: WBS↔LINK -- not individually reviewed | B29: =COUNTIF('MASTER DATA'!$I$2:$I$1624,"WBS↔LINK -- not individually reviewed")
A30: Retired -- no longer reported | B30: =COUNTIF('MASTER DATA'!$I$2:$I$1624,"Retired -- no longer reported")
A31: By relationship type
A32: ONE_TO_ONE | B32: =COUNTIF('MASTER DATA'!$F$2:$F$1624,"ONE_TO_ONE")
A33: ONE_TO_MANY | B33: =COUNTIF('MASTER DATA'!$F$2:$F$1624,"ONE_TO_MANY")
A34: NO_WBS | B34: =COUNTIF('MASTER DATA'!$F$2:$F$1624,"NO_WBS")
A35: NEW_SCOPE | B35: =COUNTIF('MASTER DATA'!$F$2:$F$1624,"NEW_SCOPE")
A36: UNSURE | B36: =COUNTIF('MASTER DATA'!$F$2:$F$1624,"UNSURE")
A37: Total rows | B37: =COUNTA('MASTER DATA'!$O$2:$O$1624)
A38: Check: basis rows add up to the total | B38: =IF(COUNTIF('MASTER DATA'!$I$2:$I$1624,"Professional decision")+COUNTIF('MASTER DATA'!$I$2:$I$1624,"Earlier professional decision, carried forward")+COUNTIF('MASTER DATA'!$I$2:$I$1624,"Source assignment -- not individually reviewed")+COUNTIF('MASTER DATA'!$I$2:$I$1624,"WBS↔LINK -- not individually reviewed")+COUNTIF('MASTER DATA'!$I$2:$I$1624,"Retired -- no longer reported")=COUNTA('MASTER DATA'!$O$2:$O$1624),"reconciled","DOES NOT RECONCILE")
A40: Canonical executive position: 03 EXECUTIVE VIEW
